{
  "bug_id": "457970",
  "summary": "AVG SafeSearch crash: Firefox 3.0.x Crash Reports in [@avgssff.dll@0x9943][@strchr | avgssff.dll@0x5546f]",
  "status": "RESOLVED",
  "resolution": "FIXED",
  "product": "Firefox",
  "component": "Extension Compatibility",
  "version": "unspecified",
  "severity": "critical",
  "priority": "P2",
  "creation_time": "2008-10-01T00:39:16Z",
  "last_change_time": "2011-06-13T17:01:47Z",
  "is_recent": false,
  "crash_signature_raw": "[@avgssff.dll@0x9943]\n[@strchr | avgssff.dll@0x5546f]",
  "crash_signatures": [
    "avgssff.dll@0x9943",
    "strchr | avgssff.dll@0x5546f"
  ],
  "keywords": [
    "crash",
    "topcrash"
  ],
  "regressed_by": [],
  "regressions": [],
  "bugzilla_url": "https://bugzilla.mozilla.org/show_bug.cgi?id=457970",
  "socorro_links": [],
  "socorro_crash_ids": [],
  "has_socorro_link": false,
  "has_direct_crash_id": false,
  "stack_traces": [
    {
      "comment_id": 3800092,
      "comment_count": 0,
      "creator": "chofmann@gmail.com",
      "creation_time": "2008-10-01T00:39:16Z",
      "raw_text": "pretty sharp increase in the number of crash reports (current ranked #7) around this stack trace.  Very similiar to https://bugzilla.mozilla.org/show_bug.cgi?id=436302 where we blocked older versions of roboform\n\n0  \tmozcrt19.dll  \tstrchr  \tstrchr.asm:101\n1 \tavgssff.dll \tavgssff.dll@0x5546f \t\n2 \tavgssff.dll \tavgssff.dll@0x22092 \t\n3 \tavgssff.dll \tavgssff.dll@0x219f6 \t\n4 \tavgssff.dll \tavgssff.dll@0x21b33 \t\n5 \txul.dll \tnsFactoryEntry::GetFactory \tmozilla/xpcom/components/nsComponentManager.cpp:3562\n6 \txul.dll \tnsComponentManagerImpl::CreateInstance \tmozilla/xpcom/components/nsComponentManager.cpp:1666\n7 \txul.dll \txul.dll@0x7b7eff\n\n(comment: On upgrade firefox will not restart) \n\nand a few with\n\n0  \tmozcrt19.dll  \tstrchr  \tstrchr.asm:101\n1 \tPlainOldFavorites.dll \tPlainOldFavorites.dll@0x4ebf \t\n2 \tPlainOldFavorites.dll \tPlainOldFavorites.dll@0x1dfb \t\n\n(comment: crashes everytime you close it.)",
      "matched_patterns": [
        "ns[A-Z]\\w+::\\w+",
        "(?i)(crash|stack)\\s*(trace|dump|report)"
      ],
      "parsed_frames": [
        {
          "frame_index": 0,
          "module": "mozcrt19.dll",
          "function": "strchr",
          "file": "strchr.asm",
          "line": 101,
          "raw": "0  \tmozcrt19.dll  \tstrchr  \tstrchr.asm:101"
        },
        {
          "frame_index": 1,
          "module": "avgssff.dll",
          "function": "avgssff.dll@0x5546f",
          "file": "",
          "line": null,
          "raw": "1 \tavgssff.dll \tavgssff.dll@0x5546f"
        },
        {
          "frame_index": 2,
          "module": "avgssff.dll",
          "function": "avgssff.dll@0x22092",
          "file": "",
          "line": null,
          "raw": "2 \tavgssff.dll \tavgssff.dll@0x22092"
        },
        {
          "frame_index": 3,
          "module": "avgssff.dll",
          "function": "avgssff.dll@0x219f6",
          "file": "",
          "line": null,
          "raw": "3 \tavgssff.dll \tavgssff.dll@0x219f6"
        },
        {
          "frame_index": 4,
          "module": "avgssff.dll",
          "function": "avgssff.dll@0x21b33",
          "file": "",
          "line": null,
          "raw": "4 \tavgssff.dll \tavgssff.dll@0x21b33"
        },
        {
          "frame_index": 5,
          "module": "xul.dll",
          "function": "nsFactoryEntry::GetFactory",
          "file": "mozilla/xpcom/components/nsComponentManager.cpp",
          "line": 3562,
          "raw": "5 \txul.dll \tnsFactoryEntry::GetFactory \tmozilla/xpcom/components/nsComponentManager.cpp:3562"
        },
        {
          "frame_index": 6,
          "module": "xul.dll",
          "function": "nsComponentManagerImpl::CreateInstance",
          "file": "mozilla/xpcom/components/nsComponentManager.cpp",
          "line": 1666,
          "raw": "6 \txul.dll \tnsComponentManagerImpl::CreateInstance \tmozilla/xpcom/components/nsComponentManager.cpp:1666"
        },
        {
          "frame_index": 7,
          "module": "xul.dll",
          "function": "xul.dll@0x7b7eff",
          "file": "",
          "line": null,
          "raw": "7 \txul.dll \txul.dll@0x7b7eff"
        },
        {
          "frame_index": 0,
          "module": "mozcrt19.dll",
          "function": "strchr",
          "file": "strchr.asm",
          "line": 101,
          "raw": "0  \tmozcrt19.dll  \tstrchr  \tstrchr.asm:101"
        },
        {
          "frame_index": 1,
          "module": "PlainOldFavorites.dll",
          "function": "PlainOldFavorites.dll@0x4ebf",
          "file": "",
          "line": null,
          "raw": "1 \tPlainOldFavorites.dll \tPlainOldFavorites.dll@0x4ebf"
        },
        {
          "frame_index": 2,
          "module": "PlainOldFavorites.dll",
          "function": "PlainOldFavorites.dll@0x1dfb",
          "file": "",
          "line": null,
          "raw": "2 \tPlainOldFavorites.dll \tPlainOldFavorites.dll@0x1dfb"
        }
      ],
      "frame_count": 11
    }
  ],
  "has_stack_traces": true,
  "stack_trace_count": 1,
  "total_parsed_frames": 11
}