{
  "bug_id": "624267",
  "summary": "Crash on Ubuntu [@ nsGNOMEShellService::SetDefaultBrowser ]",
  "status": "RESOLVED",
  "resolution": "FIXED",
  "product": "Firefox",
  "component": "Shell Integration",
  "version": "Trunk",
  "severity": "critical",
  "priority": "--",
  "creation_time": "2011-01-09T18:09:08Z",
  "last_change_time": "2011-06-13T17:01:52Z",
  "is_recent": false,
  "crash_signature_raw": "[@ nsGNOMEShellService::SetDefaultBrowser ]",
  "crash_signatures": [
    "nsGNOMEShellService::SetDefaultBrowser"
  ],
  "keywords": [
    "crash",
    "relnote",
    "topcrash"
  ],
  "regressed_by": [],
  "regressions": [],
  "bugzilla_url": "https://bugzilla.mozilla.org/show_bug.cgi?id=624267",
  "socorro_links": [],
  "socorro_crash_ids": [],
  "has_socorro_link": false,
  "has_direct_crash_id": false,
  "stack_traces": [
    {
      "comment_id": 5185864,
      "comment_count": 0,
      "creator": "scoobidiver@netcourrier.com",
      "creation_time": "2011-01-09T18:09:08Z",
      "raw_text": "It is #1 top crasher on Linux in 4.0b8 for the last week.\n\nComments say:\n\"crashed when i tried to access \"manage add ons...\" button in the preferences window.\"\n\"New installation of Ubuntu Natty - 11.04 testing. Answered 'yes' to 'do you want to set Firefox' as default browser and crash occurred immediately. Note that 11.04 is far from being stable.\"\n\"when updated beta 7 for beta8\"\n\nSignature\tnsGNOMEShellService::SetDefaultBrowser\nUUID\t0c2a2a27-2037-4496-9680-526c52110108\nTime \t2011-01-08 16:45:39.322473\nUptime\t18\nInstall Age\t18 seconds since version was first installed.\nProduct\tFirefox\nVersion\t4.0b8\nBuild ID\t20110105201936\nBranch\t2.0\nOS\tLinux\nOS Version\t0.0.0 Linux 2.6.37-7-generic #19-Ubuntu SMP Tue Nov 30 23:46:45 UTC 2010 i686\nCPU\tx86\nCPU Info\tGenuineIntel family 15 model 2 stepping 9\nCrash Reason\tSIGSEGV\nCrash Address\t0x0\n\nFrame \tModule \tSignature [Expand] \tSource\n0 \tlibbrowsercomps.so \tnsGNOMEShellService::SetDefaultBrowser \tnsGNOMEShellService.cpp:287\n1 \tlibxul.so \tlibxul.so@0xccbf0e \t\n2 \tlibxul.so \tXPCWrappedNative::CallMethod \txpcwrappednative.cpp:3064\n3 \tlibxul.so \tXPC_WN_CallMethod \txpcwrappednativejsops.cpp:1588\n4 \tlibxul.so \tjs::Interpret \tjscntxtinlines.h:684\n5 \tlibxul.so \tjs::Invoke \tjsinterp.cpp:657\n6 \tlibxul.so \tjs::ExternalInvoke \tjsinterp.cpp:858\n7 \tlibxul.so \tJS_CallFunctionValue \tjsinterp.h:962\n8 \tlibxul.so \tnsJSContext::CallEventHandler \tnsJSEnvironment.cpp:2177\n9 \tlibxul.so \tnsGlobalWindow::RunTimeout \tnsGlobalWindow.cpp:8966\n10 \tlibxul.so \tnsGlobalWindow::TimerCallback \tnsGlobalWindow.cpp:9311\n11 \tlibxul.so \tnsTimerImpl::Fire \tnsTimerImpl.cpp:425\n12 \tlibxul.so \tnsTimerEvent::Run \tnsTimerImpl.cpp:517\n13 \tlibxul.so \tnsThread::ProcessNextEvent \tnsThread.cpp:626\n14 \tlibxul.so \tNS_ProcessNextEvent_P \tnsThreadUtils.cpp:250\n15 \tlibxul.so \tmozilla::ipc::MessagePump::Run \tMessagePump.cpp:110\n16 \tlibxul.so \tMessageLoop::RunInternal \tmessage_loop.cc:219\n17 \tlibxul.so \tMessageLoop::Run \tmessage_loop.cc:202\n18 \tlibxul.so \tnsBaseAppShell::Run \tnsBaseAppShell.cpp:192\n19 \tlibxul.so \tnsAppStartup::Run \tnsAppStartup.cpp:191\n20 \tlibxul.so \tXRE_main \tnsAppRunner.cpp:3691\n21 \tfirefox-bin \tmain \tnsBrowserApp.cpp:158\n22 \tlibc-2.12.1.so \tlibc-2.12.1.so@0x16ce6 \t\n23 \tfirefox-bin \tfirefox-bin@0x10e0 \t\n24 \tfirefox-bin \tOutput \tnsBrowserApp.cpp:77\n25 \tld-2.12.1.so \tld-2.12.1.so@0xeabf \t\n\nMore reports at:\nhttp://crash-stats.mozilla.com/report/list?product=Firefox&platform=linux&query_search=signature&query_type=exact&query=&range_value=2&range_unit=weeks&hang_type=any&process_type=any&plugin_field=&plugin_query_type=&plugin_query=&do_query=1&admin=&signature=nsGNOMEShellService%3A%3ASetDefaultBrowser",
      "matched_patterns": [
        "ns[A-Z]\\w+::\\w+"
      ],
      "parsed_frames": [
        {
          "frame_index": 0,
          "module": "libbrowsercomps.so",
          "function": "nsGNOMEShellService::SetDefaultBrowser",
          "file": "nsGNOMEShellService.cpp",
          "line": 287,
          "raw": "0 \tlibbrowsercomps.so \tnsGNOMEShellService::SetDefaultBrowser \tnsGNOMEShellService.cpp:287"
        },
        {
          "frame_index": 1,
          "module": "libxul.so",
          "function": "libxul.so@0xccbf0e",
          "file": "",
          "line": null,
          "raw": "1 \tlibxul.so \tlibxul.so@0xccbf0e"
        },
        {
          "frame_index": 2,
          "module": "libxul.so",
          "function": "XPCWrappedNative::CallMethod",
          "file": "xpcwrappednative.cpp",
          "line": 3064,
          "raw": "2 \tlibxul.so \tXPCWrappedNative::CallMethod \txpcwrappednative.cpp:3064"
        },
        {
          "frame_index": 3,
          "module": "libxul.so",
          "function": "XPC_WN_CallMethod",
          "file": "xpcwrappednativejsops.cpp",
          "line": 1588,
          "raw": "3 \tlibxul.so \tXPC_WN_CallMethod \txpcwrappednativejsops.cpp:1588"
        },
        {
          "frame_index": 4,
          "module": "libxul.so",
          "function": "js::Interpret",
          "file": "jscntxtinlines.h",
          "line": 684,
          "raw": "4 \tlibxul.so \tjs::Interpret \tjscntxtinlines.h:684"
        },
        {
          "frame_index": 5,
          "module": "libxul.so",
          "function": "js::Invoke",
          "file": "jsinterp.cpp",
          "line": 657,
          "raw": "5 \tlibxul.so \tjs::Invoke \tjsinterp.cpp:657"
        },
        {
          "frame_index": 6,
          "module": "libxul.so",
          "function": "js::ExternalInvoke",
          "file": "jsinterp.cpp",
          "line": 858,
          "raw": "6 \tlibxul.so \tjs::ExternalInvoke \tjsinterp.cpp:858"
        },
        {
          "frame_index": 7,
          "module": "libxul.so",
          "function": "JS_CallFunctionValue",
          "file": "jsinterp.h",
          "line": 962,
          "raw": "7 \tlibxul.so \tJS_CallFunctionValue \tjsinterp.h:962"
        },
        {
          "frame_index": 8,
          "module": "libxul.so",
          "function": "nsJSContext::CallEventHandler",
          "file": "nsJSEnvironment.cpp",
          "line": 2177,
          "raw": "8 \tlibxul.so \tnsJSContext::CallEventHandler \tnsJSEnvironment.cpp:2177"
        },
        {
          "frame_index": 9,
          "module": "libxul.so",
          "function": "nsGlobalWindow::RunTimeout",
          "file": "nsGlobalWindow.cpp",
          "line": 8966,
          "raw": "9 \tlibxul.so \tnsGlobalWindow::RunTimeout \tnsGlobalWindow.cpp:8966"
        },
        {
          "frame_index": 10,
          "module": "libxul.so",
          "function": "nsGlobalWindow::TimerCallback",
          "file": "nsGlobalWindow.cpp",
          "line": 9311,
          "raw": "10 \tlibxul.so \tnsGlobalWindow::TimerCallback \tnsGlobalWindow.cpp:9311"
        },
        {
          "frame_index": 11,
          "module": "libxul.so",
          "function": "nsTimerImpl::Fire",
          "file": "nsTimerImpl.cpp",
          "line": 425,
          "raw": "11 \tlibxul.so \tnsTimerImpl::Fire \tnsTimerImpl.cpp:425"
        },
        {
          "frame_index": 12,
          "module": "libxul.so",
          "function": "nsTimerEvent::Run",
          "file": "nsTimerImpl.cpp",
          "line": 517,
          "raw": "12 \tlibxul.so \tnsTimerEvent::Run \tnsTimerImpl.cpp:517"
        },
        {
          "frame_index": 13,
          "module": "libxul.so",
          "function": "nsThread::ProcessNextEvent",
          "file": "nsThread.cpp",
          "line": 626,
          "raw": "13 \tlibxul.so \tnsThread::ProcessNextEvent \tnsThread.cpp:626"
        },
        {
          "frame_index": 14,
          "module": "libxul.so",
          "function": "NS_ProcessNextEvent_P",
          "file": "nsThreadUtils.cpp",
          "line": 250,
          "raw": "14 \tlibxul.so \tNS_ProcessNextEvent_P \tnsThreadUtils.cpp:250"
        },
        {
          "frame_index": 15,
          "module": "libxul.so",
          "function": "mozilla::ipc::MessagePump::Run",
          "file": "MessagePump.cpp",
          "line": 110,
          "raw": "15 \tlibxul.so \tmozilla::ipc::MessagePump::Run \tMessagePump.cpp:110"
        },
        {
          "frame_index": 16,
          "module": "libxul.so",
          "function": "MessageLoop::RunInternal",
          "file": "message_loop.cc",
          "line": 219,
          "raw": "16 \tlibxul.so \tMessageLoop::RunInternal \tmessage_loop.cc:219"
        },
        {
          "frame_index": 17,
          "module": "libxul.so",
          "function": "MessageLoop::Run",
          "file": "message_loop.cc",
          "line": 202,
          "raw": "17 \tlibxul.so \tMessageLoop::Run \tmessage_loop.cc:202"
        },
        {
          "frame_index": 18,
          "module": "libxul.so",
          "function": "nsBaseAppShell::Run",
          "file": "nsBaseAppShell.cpp",
          "line": 192,
          "raw": "18 \tlibxul.so \tnsBaseAppShell::Run \tnsBaseAppShell.cpp:192"
        },
        {
          "frame_index": 19,
          "module": "libxul.so",
          "function": "nsAppStartup::Run",
          "file": "nsAppStartup.cpp",
          "line": 191,
          "raw": "19 \tlibxul.so \tnsAppStartup::Run \tnsAppStartup.cpp:191"
        },
        {
          "frame_index": 20,
          "module": "libxul.so",
          "function": "XRE_main",
          "file": "nsAppRunner.cpp",
          "line": 3691,
          "raw": "20 \tlibxul.so \tXRE_main \tnsAppRunner.cpp:3691"
        }
      ],
      "frame_count": 21
    }
  ],
  "has_stack_traces": true,
  "stack_trace_count": 1,
  "total_parsed_frames": 21
}