{
  "bug_id": "540551",
  "summary": "[@ PayPalPlugin.dll@0x1be71][@ 0x0 | PayPalPlugin.dll@0x1be71] common null pointer dereference paypalfirefoxplugin@orbiscom",
  "status": "RESOLVED",
  "resolution": "FIXED",
  "product": "Firefox",
  "component": "Extension Compatibility",
  "version": "3.5 Branch",
  "severity": "critical",
  "priority": "--",
  "creation_time": "2010-01-19T09:11:08Z",
  "last_change_time": "2018-01-26T22:06:17Z",
  "is_recent": false,
  "crash_signature_raw": "[@ PayPalPlugin.dll@0x1be71]\r\n[@ 0x0 | PayPalPlugin.dll@0x1be71]",
  "crash_signatures": [
    "PayPalPlugin.dll@0x1be71",
    "0x0 | PayPalPlugin.dll@0x1be71"
  ],
  "keywords": [
    "crash"
  ],
  "regressed_by": [],
  "regressions": [],
  "bugzilla_url": "https://bugzilla.mozilla.org/show_bug.cgi?id=540551",
  "socorro_links": [],
  "socorro_crash_ids": [],
  "has_socorro_link": false,
  "has_direct_crash_id": false,
  "stack_traces": [
    {
      "comment_id": 4493472,
      "comment_count": 0,
      "creator": "timeless@bemail.org",
      "creation_time": "2010-01-19T09:11:08Z",
      "raw_text": "I'm filing this bug to record an instance. This crash happens fairly regularly according to crash stats. Note that we intend to blocklist paypal's extension.\n\nFor a random day, we had crashes from 2.2.26.0 and 2.2.19.0:\n  PayPalPlugin.dll@0x1be71|EXCEPTION_ACCESS_VIOLATION (12 crashes)\n    100% (12/12) vs.   0% (268/89657) paypalfirefoxplugin@orbiscom\n         92% (11/12) vs.   0% (33/89657) 2.2.19.0\n          8% (1/12) vs.   0% (218/89657) 2.2.26.0\nI can't find the 2.2.26.0 crash in the database, \n\n\nSignature\tPayPalPlugin.dll@0x1be71\nUUID\t76c84078-539d-4a44-8049-dcbd52100115\nTime \t2010-01-15 08:55:52.758363\nUptime\t6744\nLast Crash\t5427543 seconds before submission\nProduct\tFirefox\nVersion\t3.5.7\nBuild ID\t20091221164558\nBranch\t1.9.1\nOS\tWindows NT\nOS Version\t6.0.6002 Service Pack 2\nCPU\tx86\nCPU Info\tAuthenticAMD family 15 model 127 stepping 2\nCrash Reason\tEXCEPTION_ACCESS_VIOLATION\nCrash Address\t0x0\nUser Comments\tit crashed when I clicked on 'customize your firefox' if that helps. It does crash more than Google. AND I only use Firefox for paypal 'cause it lets me do more, than when I use Google. I would use FireFox for everything but it's sooooooooooooo slooooooooow in ebay. That's about the only reason I use the PC, for ebay, selling. (I do clear my cookies,too) You don't have to email me back, or start me up, this is a good time to say how slow Firefox is & maybe you can make it faster(I hope)\nProcessor Notes \t\nCrashing Thread\nFrame \tModule \tSignature [Expand] \tSource\n0 \tPayPalPlugin.dll \tPayPalPlugin.dll@0x1be71 \t\n1 \tPayPalPlugin.dll \tPayPalPlugin.dll@0x225e3 \t\n2 \tPayPalPlugin.dll \tPayPalPlugin.dll@0x1ed50 \t\n3 \tPayPalPlugin.dll \tPayPalPlugin.dll@0x1f1f5 \t\n4 \tPayPalPlugin.dll \tPayPalPlugin.dll@0x1ce74 \t\n5 \tuser32.dll \tInternalCallWinProc \t\n6 \tuser32.dll \tUserCallWinProcCheckWow \t\n7 \tuser32.dll \tDispatchMessageWorker \t\n8 \tuser32.dll \tDispatchMessageW \t\n9 \txul.dll \tnsAppShell::ProcessNextNativeEvent \twidget/src/windows/nsAppShell.cpp:165\n10 \twinmm.dll \ttimeGetTime \t\n11 \txul.dll \tnsBaseAppShell::OnProcessNextEvent \twidget/src/xpwidgets/nsBaseAppShell.cpp:296\n12 \tnspr4.dll \tnspr4.dll@0x1546f \t\n13 \txul.dll \tnsThread::ProcessNextEvent \txpcom/threads/nsThread.cpp:508\n14 \txul.dll \tnsBaseAppShell::Run \twidget/src/xpwidgets/nsBaseAppShell.cpp:170\n15 \txul.dll \tnsAppStartup::Run \ttoolkit/components/startup/src/nsAppStartup.cpp:193\n16 \tnspr4.dll \tPR_GetEnv \t\n17 \tfirefox.exe \twmain \ttoolkit/xre/nsWindowsWMain.cpp:110\n18 \tfirefox.exe \t__tmainCRTStartup \tobj-firefox/memory/jemalloc/src/crtexe.c:591\n19 \tkernel32.dll \tBaseThreadInitThunk \t\n20 \tntdll.dll \t__RtlUserThreadStart \t\n21 \tntdll.dll \t_RtlUserThreadStart \t\n\nFilename \tVersion \tDebug Identifier \tDebug Filename\nPayPalPlugin.dll \t2.2.19.0 \t\t\n\nExtension \tExtension Id \tVersion \tCurrent?\n\tpaypalfirefoxplugin@orbiscom \t2.2.19.0",
      "matched_patterns": [
        "ns[A-Z]\\w+::\\w+",
        "(?i)crashing\\s+thread"
      ],
      "parsed_frames": [
        {
          "frame_index": 0,
          "module": "PayPalPlugin.dll",
          "function": "PayPalPlugin.dll@0x1be71",
          "file": "",
          "line": null,
          "raw": "0 \tPayPalPlugin.dll \tPayPalPlugin.dll@0x1be71"
        },
        {
          "frame_index": 1,
          "module": "PayPalPlugin.dll",
          "function": "PayPalPlugin.dll@0x225e3",
          "file": "",
          "line": null,
          "raw": "1 \tPayPalPlugin.dll \tPayPalPlugin.dll@0x225e3"
        },
        {
          "frame_index": 2,
          "module": "PayPalPlugin.dll",
          "function": "PayPalPlugin.dll@0x1ed50",
          "file": "",
          "line": null,
          "raw": "2 \tPayPalPlugin.dll \tPayPalPlugin.dll@0x1ed50"
        },
        {
          "frame_index": 3,
          "module": "PayPalPlugin.dll",
          "function": "PayPalPlugin.dll@0x1f1f5",
          "file": "",
          "line": null,
          "raw": "3 \tPayPalPlugin.dll \tPayPalPlugin.dll@0x1f1f5"
        },
        {
          "frame_index": 4,
          "module": "PayPalPlugin.dll",
          "function": "PayPalPlugin.dll@0x1ce74",
          "file": "",
          "line": null,
          "raw": "4 \tPayPalPlugin.dll \tPayPalPlugin.dll@0x1ce74"
        },
        {
          "frame_index": 5,
          "module": "user32.dll",
          "function": "InternalCallWinProc",
          "file": "",
          "line": null,
          "raw": "5 \tuser32.dll \tInternalCallWinProc"
        },
        {
          "frame_index": 6,
          "module": "user32.dll",
          "function": "UserCallWinProcCheckWow",
          "file": "",
          "line": null,
          "raw": "6 \tuser32.dll \tUserCallWinProcCheckWow"
        },
        {
          "frame_index": 7,
          "module": "user32.dll",
          "function": "DispatchMessageWorker",
          "file": "",
          "line": null,
          "raw": "7 \tuser32.dll \tDispatchMessageWorker"
        },
        {
          "frame_index": 8,
          "module": "user32.dll",
          "function": "DispatchMessageW",
          "file": "",
          "line": null,
          "raw": "8 \tuser32.dll \tDispatchMessageW"
        },
        {
          "frame_index": 9,
          "module": "xul.dll",
          "function": "nsAppShell::ProcessNextNativeEvent",
          "file": "widget/src/windows/nsAppShell.cpp",
          "line": 165,
          "raw": "9 \txul.dll \tnsAppShell::ProcessNextNativeEvent \twidget/src/windows/nsAppShell.cpp:165"
        },
        {
          "frame_index": 10,
          "module": "winmm.dll",
          "function": "timeGetTime",
          "file": "",
          "line": null,
          "raw": "10 \twinmm.dll \ttimeGetTime"
        },
        {
          "frame_index": 11,
          "module": "xul.dll",
          "function": "nsBaseAppShell::OnProcessNextEvent",
          "file": "widget/src/xpwidgets/nsBaseAppShell.cpp",
          "line": 296,
          "raw": "11 \txul.dll \tnsBaseAppShell::OnProcessNextEvent \twidget/src/xpwidgets/nsBaseAppShell.cpp:296"
        },
        {
          "frame_index": 12,
          "module": "nspr4.dll",
          "function": "nspr4.dll@0x1546f",
          "file": "",
          "line": null,
          "raw": "12 \tnspr4.dll \tnspr4.dll@0x1546f"
        },
        {
          "frame_index": 13,
          "module": "xul.dll",
          "function": "nsThread::ProcessNextEvent",
          "file": "xpcom/threads/nsThread.cpp",
          "line": 508,
          "raw": "13 \txul.dll \tnsThread::ProcessNextEvent \txpcom/threads/nsThread.cpp:508"
        },
        {
          "frame_index": 14,
          "module": "xul.dll",
          "function": "nsBaseAppShell::Run",
          "file": "widget/src/xpwidgets/nsBaseAppShell.cpp",
          "line": 170,
          "raw": "14 \txul.dll \tnsBaseAppShell::Run \twidget/src/xpwidgets/nsBaseAppShell.cpp:170"
        },
        {
          "frame_index": 15,
          "module": "xul.dll",
          "function": "nsAppStartup::Run",
          "file": "toolkit/components/startup/src/nsAppStartup.cpp",
          "line": 193,
          "raw": "15 \txul.dll \tnsAppStartup::Run \ttoolkit/components/startup/src/nsAppStartup.cpp:193"
        },
        {
          "frame_index": 16,
          "module": "nspr4.dll",
          "function": "PR_GetEnv",
          "file": "",
          "line": null,
          "raw": "16 \tnspr4.dll \tPR_GetEnv"
        },
        {
          "frame_index": 19,
          "module": "kernel32.dll",
          "function": "BaseThreadInitThunk",
          "file": "",
          "line": null,
          "raw": "19 \tkernel32.dll \tBaseThreadInitThunk"
        },
        {
          "frame_index": 20,
          "module": "ntdll.dll",
          "function": "__RtlUserThreadStart",
          "file": "",
          "line": null,
          "raw": "20 \tntdll.dll \t__RtlUserThreadStart"
        },
        {
          "frame_index": 21,
          "module": "ntdll.dll",
          "function": "_RtlUserThreadStart",
          "file": "",
          "line": null,
          "raw": "21 \tntdll.dll \t_RtlUserThreadStart"
        }
      ],
      "frame_count": 20
    }
  ],
  "has_stack_traces": true,
  "stack_trace_count": 1,
  "total_parsed_frames": 20
}