{
  "bug_id": "1383405",
  "summary": "Firefox Headless crash on linux [@ mozilla::gl::GLXLibrary::EnsureInitialized]",
  "status": "RESOLVED",
  "resolution": "FIXED",
  "product": "Firefox",
  "component": "Headless",
  "version": "56 Branch",
  "severity": "critical",
  "priority": "--",
  "creation_time": "2017-07-22T13:18:27Z",
  "last_change_time": "2017-08-11T02:51:58Z",
  "is_recent": false,
  "crash_signature_raw": "[@ mozilla::gl::GLXLibrary::EnsureInitialized]",
  "crash_signatures": [
    "mozilla::gl::GLXLibrary::EnsureInitialized"
  ],
  "keywords": [
    "crash"
  ],
  "regressed_by": [],
  "regressions": [],
  "bugzilla_url": "https://bugzilla.mozilla.org/show_bug.cgi?id=1383405",
  "socorro_links": [],
  "socorro_crash_ids": [],
  "has_socorro_link": false,
  "has_direct_crash_id": false,
  "stack_traces": [
    {
      "comment_id": 12528884,
      "comment_count": 2,
      "creator": "hskupin@gmail.com",
      "creation_time": "2017-08-02T12:22:20Z",
      "raw_text": "Here the first 10 frames from the crashing thread:\n\n0 \tlibxul.so \tmozilla::gl::GLXLibrary::EnsureInitialized \tgfx/gl/GLContextProviderGLX.cpp:140\n1 \tlibxul.so \tmozilla::gl::GLXLibrary::SupportsVideoSync \tgfx/gl/GLContextProviderGLX.cpp:247\n2 \tlibxul.so \tlibxul.so@0x1130e8f \t\n3 \tlibxul.so \tgfxPlatform::Init() \t\n4 \tlibxul.so \tgfxPlatform::GetPlatform() \t\n5 \tlibxul.so \tmozilla::widget::GfxInfoBase::GetContentBackend(nsAString&) \t\n6 \tlibxul.so \tNS_InvokeByIndex \t\n7 \tlibxul.so \tXPCWrappedNative::CallMethod(XPCCallContext&, XPCWrappedNative::CallMode) \t\n8 \tlibxul.so \tXPC_WN_GetterSetter(JSContext*, unsigned int, JS::Value*) \t\n9 \tlibxul.so \tjs::InternalCallOrConstruct(JSContext*, JS::CallArgs const&, js::MaybeConstruct) \t\n10 \tlibxul.so \tjs::CallGetter(JSContext*, JS::Handle<JS::Value>, JS::Handle<JS::Value>, JS::MutableHandle<JS::Value>)\n\nDaniele, can you please attach the output from about:support to this bug?",
      "matched_patterns": [
        "mozilla::\\S+::\\S+\\s*\\(",
        "(?i)crashing\\s+thread"
      ],
      "parsed_frames": [
        {
          "frame_index": 0,
          "module": "libxul.so",
          "function": "mozilla::gl::GLXLibrary::EnsureInitialized",
          "file": "gfx/gl/GLContextProviderGLX.cpp",
          "line": 140,
          "raw": "0 \tlibxul.so \tmozilla::gl::GLXLibrary::EnsureInitialized \tgfx/gl/GLContextProviderGLX.cpp:140"
        },
        {
          "frame_index": 1,
          "module": "libxul.so",
          "function": "mozilla::gl::GLXLibrary::SupportsVideoSync",
          "file": "gfx/gl/GLContextProviderGLX.cpp",
          "line": 247,
          "raw": "1 \tlibxul.so \tmozilla::gl::GLXLibrary::SupportsVideoSync \tgfx/gl/GLContextProviderGLX.cpp:247"
        },
        {
          "frame_index": 2,
          "module": "libxul.so",
          "function": "libxul.so@0x1130e8f",
          "file": "",
          "line": null,
          "raw": "2 \tlibxul.so \tlibxul.so@0x1130e8f"
        },
        {
          "frame_index": 3,
          "module": "libxul.so",
          "function": "gfxPlatform::Init()",
          "file": "",
          "line": null,
          "raw": "3 \tlibxul.so \tgfxPlatform::Init()"
        },
        {
          "frame_index": 4,
          "module": "libxul.so",
          "function": "gfxPlatform::GetPlatform()",
          "file": "",
          "line": null,
          "raw": "4 \tlibxul.so \tgfxPlatform::GetPlatform()"
        },
        {
          "frame_index": 5,
          "module": "libxul.so",
          "function": "mozilla::widget::GfxInfoBase::GetContentBackend(nsAString&)",
          "file": "",
          "line": null,
          "raw": "5 \tlibxul.so \tmozilla::widget::GfxInfoBase::GetContentBackend(nsAString&)"
        },
        {
          "frame_index": 6,
          "module": "libxul.so",
          "function": "NS_InvokeByIndex",
          "file": "",
          "line": null,
          "raw": "6 \tlibxul.so \tNS_InvokeByIndex"
        },
        {
          "frame_index": 7,
          "module": "libxul.so",
          "function": "XPCWrappedNative::CallMethod(XPCCallContext&, XPCWrappedNative::CallMode)",
          "file": "",
          "line": null,
          "raw": "7 \tlibxul.so \tXPCWrappedNative::CallMethod(XPCCallContext&, XPCWrappedNative::CallMode)"
        },
        {
          "frame_index": 8,
          "module": "libxul.so",
          "function": "XPC_WN_GetterSetter(JSContext*, unsigned int, JS::Value*)",
          "file": "",
          "line": null,
          "raw": "8 \tlibxul.so \tXPC_WN_GetterSetter(JSContext*, unsigned int, JS::Value*)"
        },
        {
          "frame_index": 9,
          "module": "libxul.so",
          "function": "js::InternalCallOrConstruct(JSContext*, JS::CallArgs const&, js::MaybeConstruct)",
          "file": "",
          "line": null,
          "raw": "9 \tlibxul.so \tjs::InternalCallOrConstruct(JSContext*, JS::CallArgs const&, js::MaybeConstruct)"
        },
        {
          "frame_index": 10,
          "module": "libxul.so",
          "function": "js::CallGetter(JSContext*, JS::Handle<JS::Value>, JS::Handle<JS::Value>, JS::MutableHandle<JS::Value>)",
          "file": "",
          "line": null,
          "raw": "10 \tlibxul.so \tjs::CallGetter(JSContext*, JS::Handle<JS::Value>, JS::Handle<JS::Value>, JS::MutableHandle<JS::Value>)"
        }
      ],
      "frame_count": 11
    }
  ],
  "has_stack_traces": true,
  "stack_trace_count": 1,
  "total_parsed_frames": 11
}