{
  "bug_id": "629634",
  "summary": "Crash [@ ffplugin.dll@0x19d0c4 ][@ _purecall | ffplugin.dll@0x19d0c8 ][@ ffplugin.dll@0x19caa4 ][@ ffplugin.dll@0x19cf04 ][@ ffplugin.dll@0x173ee4 ][@ ffplugin.dll@0x174524 ][@ ffplugin.dll@0x175244 ][@ ffplugin.dll@0x173ed4 ] with Bandoo 5.0 or 6.0",
  "status": "RESOLVED",
  "resolution": "FIXED",
  "product": "Firefox",
  "component": "Extension Compatibility",
  "version": "unspecified",
  "severity": "critical",
  "priority": "--",
  "creation_time": "2011-01-28T10:39:20Z",
  "last_change_time": "2022-09-08T15:48:28Z",
  "is_recent": false,
  "crash_signature_raw": "[@ ffplugin.dll@0x19d0c4 ]\n[@ _purecall | ffplugin.dll@0x19d0c8 ]\n[@ ffplugin.dll@0x19caa4 ]\n[@ ffplugin.dll@0x19cf04 ]\n[@ ffplugin.dll@0x173ee4 ]\n[@ ffplugin.dll@0x174524 ]\n[@ ffplugin.dll@0x175244 ]\n[@ ffplugin.dll@0x173ed4 ]",
  "crash_signatures": [
    "ffplugin.dll@0x19d0c4",
    "_purecall | ffplugin.dll@0x19d0c8",
    "ffplugin.dll@0x19caa4",
    "ffplugin.dll@0x19cf04",
    "ffplugin.dll@0x173ee4",
    "ffplugin.dll@0x174524",
    "ffplugin.dll@0x175244",
    "ffplugin.dll@0x173ed4"
  ],
  "keywords": [
    "crash",
    "topcrash"
  ],
  "regressed_by": [],
  "regressions": [],
  "bugzilla_url": "https://bugzilla.mozilla.org/show_bug.cgi?id=629634",
  "socorro_links": [],
  "socorro_crash_ids": [],
  "has_socorro_link": false,
  "has_direct_crash_id": false,
  "stack_traces": [
    {
      "comment_id": 5234892,
      "comment_count": 0,
      "creator": "scoobidiver@netcourrier.com",
      "creation_time": "2011-01-28T10:39:20Z",
      "raw_text": "It is a residual crash signature that exists in 3.6 and the trunk.\nWith combined signature, it is #8 top crasher in 4.0b10.\nI guess it is a Bandoo bug and not a Javacript one.\n\nSignature\tFFPlugin.dll@0x19d0c4\nUUID\t84612a98-ed7b-4aa4-a4af-da55b2110127\nTime \t2011-01-27 22:02:13.721380\nUptime\t8049\nLast Crash\t49259 seconds (13.7 hours) before submission\nInstall Age\t97714 seconds (1.1 days) since version was first installed.\nProduct\tFirefox\nVersion\t4.0b10\nBuild ID\t20110121161358\nBranch\t2.0\nOS\tWindows NT\nOS Version\t5.1.2600 Service Pack 3\nCPU\tx86\nCPU Info\tGenuineIntel family 6 model 15 stepping 13\nCrash Reason\tEXCEPTION_ACCESS_VIOLATION_READ\nCrash Address\t0x9\nApp Notes \tAdapterVendorID: 8086, AdapterDeviceID: 2772, AdapterDriverVersion: 6.14.10.4906\n\nFrame \tModule \tSignature [Expand] \tSource\n0 \tFFPlugin.dll \tFFPlugin.dll@0x19d0c4 \t\n1 \txul.dll \tNS_InvokeByIndex_P \txpcom/reflect/xptcall/src/md/win32/xptcinvoke.cpp:102\n2 \txul.dll \tXPC_WN_CallMethod \tjs/src/xpconnect/src/xpcwrappednativejsops.cpp:1593\n3 \tmozjs.dll \tCallCompiler::generateNativeStub \tjs/src/methodjit/MonoIC.cpp:666\n4 \tmozjs.dll \tjs::mjit::ic::NativeCall \tjs/src/methodjit/MonoIC.cpp:873\n5 \t\t@0x1e2adb5d \t\n6 \tmozjs.dll \tjs::mjit::EnterMethodJIT \tjs/src/methodjit/MethodJIT.cpp:748\n7 \tmozjs.dll \tCheckStackAndEnterMethodJIT \tjs/src/methodjit/MethodJIT.cpp:774\n8 \tmozjs.dll \tjs::mjit::JaegerShot \tjs/src/methodjit/MethodJIT.cpp:791\n9 \tmozjs.dll \tjs::RunScript \tjs/src/jsinterp.cpp:654\n10 \tmozjs.dll \tjs::Invoke \tjs/src/jsinterp.cpp:737\n11 \tmozjs.dll \tjs::ExternalInvoke \tjs/src/jsinterp.cpp:858\n12 \tmozjs.dll \tjs::JSProxyHandler::call \tjs/src/jsproxy.cpp:248\n13 \tmozjs.dll \tJSCrossCompartmentWrapper::call \tjs/src/jswrapper.cpp:601\n14 \tmozjs.dll \tjs::JSProxy::call \tjs/src/jsproxy.cpp:810\n15 \tmozjs.dll \tjs::proxy_Call \tjs/src/jsproxy.cpp:1062\n16 \tmozjs.dll \tjs::Invoke \tjs/src/jsinterp.cpp:693\n17 \tmozjs.dll \tjs::ExternalInvoke \tjs/src/jsinterp.cpp:858\n18 \tmozjs.dll \tJS_CallFunctionValue \tjs/src/jsapi.cpp:5019\n19 \txul.dll \tnsXPCWrappedJSClass::CallMethod \tjs/src/xpconnect/src/xpcwrappedjsclass.cpp:1700\n20 \txul.dll \tnsXPCWrappedJS::CallMethod \tjs/src/xpconnect/src/xpcwrappedjs.cpp:588\n21 \txul.dll \tPrepareAndDispatch \txpcom/reflect/xptcall/src/md/win32/xptcstubs.cpp:114\n22 \txul.dll \tSharedStub \txpcom/reflect/xptcall/src/md/win32/xptcstubs.cpp:141\n23 \txul.dll \tnsEventListenerManager::HandleEventSubType \tcontent/events/src/nsEventListenerManager.cpp:1114\n\nMore reports at:\nhttp://crash-stats.mozilla.com/report/list?range_value=2&range_unit=weeks&signature=FFPlugin.dll%400x19d0c4\nhttp://crash-stats.mozilla.com/report/list?range_value=2&range_unit=weeks&signature=_purecall%20|%20FFPlugin.dll%400x19d0c8\nhttp://crash-stats.mozilla.com/report/list?range_value=2&range_unit=weeks&signature=FFPlugin.dll%400x19caa4",
      "matched_patterns": [
        "ns[A-Z]\\w+::\\w+"
      ],
      "parsed_frames": [
        {
          "frame_index": 0,
          "module": "FFPlugin.dll",
          "function": "FFPlugin.dll@0x19d0c4",
          "file": "",
          "line": null,
          "raw": "0 \tFFPlugin.dll \tFFPlugin.dll@0x19d0c4"
        },
        {
          "frame_index": 1,
          "module": "xul.dll",
          "function": "NS_InvokeByIndex_P",
          "file": "xpcom/reflect/xptcall/src/md/win32/xptcinvoke.cpp",
          "line": 102,
          "raw": "1 \txul.dll \tNS_InvokeByIndex_P \txpcom/reflect/xptcall/src/md/win32/xptcinvoke.cpp:102"
        },
        {
          "frame_index": 2,
          "module": "xul.dll",
          "function": "XPC_WN_CallMethod",
          "file": "js/src/xpconnect/src/xpcwrappednativejsops.cpp",
          "line": 1593,
          "raw": "2 \txul.dll \tXPC_WN_CallMethod \tjs/src/xpconnect/src/xpcwrappednativejsops.cpp:1593"
        },
        {
          "frame_index": 3,
          "module": "mozjs.dll",
          "function": "CallCompiler::generateNativeStub",
          "file": "js/src/methodjit/MonoIC.cpp",
          "line": 666,
          "raw": "3 \tmozjs.dll \tCallCompiler::generateNativeStub \tjs/src/methodjit/MonoIC.cpp:666"
        },
        {
          "frame_index": 4,
          "module": "mozjs.dll",
          "function": "js::mjit::ic::NativeCall",
          "file": "js/src/methodjit/MonoIC.cpp",
          "line": 873,
          "raw": "4 \tmozjs.dll \tjs::mjit::ic::NativeCall \tjs/src/methodjit/MonoIC.cpp:873"
        },
        {
          "frame_index": 6,
          "module": "mozjs.dll",
          "function": "js::mjit::EnterMethodJIT",
          "file": "js/src/methodjit/MethodJIT.cpp",
          "line": 748,
          "raw": "6 \tmozjs.dll \tjs::mjit::EnterMethodJIT \tjs/src/methodjit/MethodJIT.cpp:748"
        },
        {
          "frame_index": 7,
          "module": "mozjs.dll",
          "function": "CheckStackAndEnterMethodJIT",
          "file": "js/src/methodjit/MethodJIT.cpp",
          "line": 774,
          "raw": "7 \tmozjs.dll \tCheckStackAndEnterMethodJIT \tjs/src/methodjit/MethodJIT.cpp:774"
        },
        {
          "frame_index": 8,
          "module": "mozjs.dll",
          "function": "js::mjit::JaegerShot",
          "file": "js/src/methodjit/MethodJIT.cpp",
          "line": 791,
          "raw": "8 \tmozjs.dll \tjs::mjit::JaegerShot \tjs/src/methodjit/MethodJIT.cpp:791"
        },
        {
          "frame_index": 9,
          "module": "mozjs.dll",
          "function": "js::RunScript",
          "file": "js/src/jsinterp.cpp",
          "line": 654,
          "raw": "9 \tmozjs.dll \tjs::RunScript \tjs/src/jsinterp.cpp:654"
        },
        {
          "frame_index": 10,
          "module": "mozjs.dll",
          "function": "js::Invoke",
          "file": "js/src/jsinterp.cpp",
          "line": 737,
          "raw": "10 \tmozjs.dll \tjs::Invoke \tjs/src/jsinterp.cpp:737"
        },
        {
          "frame_index": 11,
          "module": "mozjs.dll",
          "function": "js::ExternalInvoke",
          "file": "js/src/jsinterp.cpp",
          "line": 858,
          "raw": "11 \tmozjs.dll \tjs::ExternalInvoke \tjs/src/jsinterp.cpp:858"
        },
        {
          "frame_index": 12,
          "module": "mozjs.dll",
          "function": "js::JSProxyHandler::call",
          "file": "js/src/jsproxy.cpp",
          "line": 248,
          "raw": "12 \tmozjs.dll \tjs::JSProxyHandler::call \tjs/src/jsproxy.cpp:248"
        },
        {
          "frame_index": 13,
          "module": "mozjs.dll",
          "function": "JSCrossCompartmentWrapper::call",
          "file": "js/src/jswrapper.cpp",
          "line": 601,
          "raw": "13 \tmozjs.dll \tJSCrossCompartmentWrapper::call \tjs/src/jswrapper.cpp:601"
        },
        {
          "frame_index": 14,
          "module": "mozjs.dll",
          "function": "js::JSProxy::call",
          "file": "js/src/jsproxy.cpp",
          "line": 810,
          "raw": "14 \tmozjs.dll \tjs::JSProxy::call \tjs/src/jsproxy.cpp:810"
        },
        {
          "frame_index": 15,
          "module": "mozjs.dll",
          "function": "js::proxy_Call",
          "file": "js/src/jsproxy.cpp",
          "line": 1062,
          "raw": "15 \tmozjs.dll \tjs::proxy_Call \tjs/src/jsproxy.cpp:1062"
        },
        {
          "frame_index": 16,
          "module": "mozjs.dll",
          "function": "js::Invoke",
          "file": "js/src/jsinterp.cpp",
          "line": 693,
          "raw": "16 \tmozjs.dll \tjs::Invoke \tjs/src/jsinterp.cpp:693"
        },
        {
          "frame_index": 17,
          "module": "mozjs.dll",
          "function": "js::ExternalInvoke",
          "file": "js/src/jsinterp.cpp",
          "line": 858,
          "raw": "17 \tmozjs.dll \tjs::ExternalInvoke \tjs/src/jsinterp.cpp:858"
        },
        {
          "frame_index": 18,
          "module": "mozjs.dll",
          "function": "JS_CallFunctionValue",
          "file": "js/src/jsapi.cpp",
          "line": 5019,
          "raw": "18 \tmozjs.dll \tJS_CallFunctionValue \tjs/src/jsapi.cpp:5019"
        },
        {
          "frame_index": 19,
          "module": "xul.dll",
          "function": "nsXPCWrappedJSClass::CallMethod",
          "file": "js/src/xpconnect/src/xpcwrappedjsclass.cpp",
          "line": 1700,
          "raw": "19 \txul.dll \tnsXPCWrappedJSClass::CallMethod \tjs/src/xpconnect/src/xpcwrappedjsclass.cpp:1700"
        },
        {
          "frame_index": 20,
          "module": "xul.dll",
          "function": "nsXPCWrappedJS::CallMethod",
          "file": "js/src/xpconnect/src/xpcwrappedjs.cpp",
          "line": 588,
          "raw": "20 \txul.dll \tnsXPCWrappedJS::CallMethod \tjs/src/xpconnect/src/xpcwrappedjs.cpp:588"
        },
        {
          "frame_index": 21,
          "module": "xul.dll",
          "function": "PrepareAndDispatch",
          "file": "xpcom/reflect/xptcall/src/md/win32/xptcstubs.cpp",
          "line": 114,
          "raw": "21 \txul.dll \tPrepareAndDispatch \txpcom/reflect/xptcall/src/md/win32/xptcstubs.cpp:114"
        },
        {
          "frame_index": 22,
          "module": "xul.dll",
          "function": "SharedStub",
          "file": "xpcom/reflect/xptcall/src/md/win32/xptcstubs.cpp",
          "line": 141,
          "raw": "22 \txul.dll \tSharedStub \txpcom/reflect/xptcall/src/md/win32/xptcstubs.cpp:141"
        },
        {
          "frame_index": 23,
          "module": "xul.dll",
          "function": "nsEventListenerManager::HandleEventSubType",
          "file": "content/events/src/nsEventListenerManager.cpp",
          "line": 1114,
          "raw": "23 \txul.dll \tnsEventListenerManager::HandleEventSubType \tcontent/events/src/nsEventListenerManager.cpp:1114"
        }
      ],
      "frame_count": 23
    }
  ],
  "has_stack_traces": true,
  "stack_trace_count": 1,
  "total_parsed_frames": 23
}