{
  "bug_id": "789700",
  "summary": "crash in vmsfdmff.dll@0x572. with Free Download Manager 1.5.7.6 and below",
  "status": "RESOLVED",
  "resolution": "FIXED",
  "product": "Firefox",
  "component": "Extension Compatibility",
  "version": "17 Branch",
  "severity": "critical",
  "priority": "--",
  "creation_time": "2012-09-08T15:03:57Z",
  "last_change_time": "2019-12-02T11:36:45Z",
  "is_recent": false,
  "crash_signature_raw": "[@ vmsfdmff.dll@0x5728]\r\n[@ vmsfdmff.dll@0x5729]",
  "crash_signatures": [
    "vmsfdmff.dll@0x5728",
    "vmsfdmff.dll@0x5729"
  ],
  "keywords": [
    "crash"
  ],
  "regressed_by": [],
  "regressions": [],
  "bugzilla_url": "https://bugzilla.mozilla.org/show_bug.cgi?id=789700",
  "socorro_links": [],
  "socorro_crash_ids": [],
  "has_socorro_link": false,
  "has_direct_crash_id": false,
  "stack_traces": [
    {
      "comment_id": 6620300,
      "comment_count": 0,
      "creator": "scoobidiver@netcourrier.com",
      "creation_time": "2012-09-08T15:03:57Z",
      "raw_text": "It's #118 top browser crasher in 15.0 and #29 in 15.0.1.\n\nHere are correlations in 15.0:\n  vmsfdmff.dll@0x5728|EXCEPTION_ACCESS_VIOLATION_EXEC (63 crashes)\n    100% (63/63) vs.   0% (109/85590) vmsfdmff.dll\n        100% (63/63) vs.   0% (105/85590) 1260.0.0.0\n  vmsfdmff.dll@0x5728|EXCEPTION_ACCESS_VIOLATION_EXEC (63 crashes)\n     98% (62/63) vs.   0% (115/85590) fdm_ffext@freedownloadmanager.org\n         98% (62/63) vs.   0% (109/85590) 1.5.7.5\n\nSignature \tvmsfdmff.dll@0x5728 More Reports Search\nUUID\t355d7a8b-b3c1-4336-940b-deca52120908\nDate Processed\t2012-09-08 07:01:52\nUptime\t320\nLast Crash\t5.6 minutes before submission\nInstall Age\t58.5 minutes since version was first installed.\nInstall Time\t2012-09-08 05:01:29\nProduct\tFirefox\nVersion\t15.0.1\nBuild ID\t20120905151427\nRelease Channel\trelease\nOS\tWindows NT\nOS Version\t5.1.2600 Service Pack 3\nBuild Architecture\tx86\nBuild Architecture Info\tAuthenticAMD family 16 model 5 stepping 3\nCrash Reason\tEXCEPTION_ACCESS_VIOLATION_READ\nCrash Address\t0xffffffff8370bf59\nUser Comments\t\u0421\u0440\u044b\u0432\u044b \u043f\u0438\u0440 \u043f\u043e\u043f\u044b\u0442\u043a\u0435 \u0437\u0430\u0433\u0440\u0443\u0437\u043a\u0438 \u043a\u043d\u0438\u0433\u0438\nApp Notes \t\nAdapterVendorID: 0x10de, AdapterDeviceID: 0x1245, AdapterSubsysID: 00000000, AdapterDriverVersion: 6.14.12.8558\nD3D10 Layers? D3D10 Layers- D3D9 Layers? D3D9 Layers+ \nEMCheckCompatibility\tTrue\nAdapter Vendor ID\t0x10de\nAdapter Device ID\t0x1245\nTotal Virtual Memory\t2147352576\nAvailable Virtual Memory\t1721196544\nSystem Memory Use Percentage\t46\nAvailable Page File\t3370094592\nAvailable Physical Memory\t1158504448\n\nFrame \tModule \tSignature \tSource\n0 \t\t@0x8370bf59 \t\n1 \tvmsfdmff.dll \tvmsfdmff.dll@0x5728 \t\n2 \tvmsfdmff.dll \tvmsfdmff.dll@0x38f6 \t\n3 \tvmsfdmff.dll \tvmsfdmff.dll@0x3f69 \t\n4 \txul.dll \tNS_InvokeByIndex_P \txpcom/reflect/xptcall/src/md/win32/xptcinvoke.cpp:70\n5 \txul.dll \tXPCWrappedNative::CallMethod \tjs/xpconnect/src/XPCWrappedNative.cpp:2442\n6 \txul.dll \tXPC_WN_CallMethod \tjs/xpconnect/src/XPCWrappedNativeJSOps.cpp:1500\n7 \tmozjs.dll \tjs::InvokeKernel \tjs/src/jsinterp.cpp:313\n8 \tmozjs.dll \tjs::Interpret \tjs/src/jsinterp.cpp:2515\n9 \tmozjs.dll \tjs::InvokeKernel \tjs/src/jsinterp.cpp:329\n10 \tmozjs.dll \tjs::Invoke \tjs/src/jsinterp.cpp:361\n11 \tmozjs.dll \tJS_CallFunctionValue \tjs/src/jsapi.cpp:5549\n12 \txul.dll \tnsXPCWrappedJSClass::CallMethod \tjs/xpconnect/src/XPCWrappedJSClass.cpp:1474\n13 \txul.dll \tXPCVariant::`scalar deleting destructor' \t\n14 \txul.dll \tnsJSEventListener::HandleEvent \tdom/src/events/nsJSEventListener.cpp:141\n15 \txul.dll \tnsEventListenerManager::HandleEventInternal \tcontent/events/src/nsEventListenerManager.cpp:868\n16 \txul.dll \tnsEventTargetChainItem::HandleEventTargetChain \tcontent/events/src/nsEventDispatcher.cpp:317\n17 \txul.dll \tnsEventDispatcher::Dispatch \tcontent/events/src/nsEventDispatcher.cpp:643\n18 \txul.dll \tDocumentViewerImpl::LoadComplete \tlayout/base/nsDocumentViewer.cpp:1023\n19 \txul.dll \tnsDocShell::EndPageLoad \tdocshell/base/nsDocShell.cpp:6239\n....\n\nMore reports at:\nhttps://crash-stats.mozilla.com/report/list?signature=vmsfdmff.dll%400x5728",
      "matched_patterns": [
        "ns[A-Z]\\w+::\\w+"
      ],
      "parsed_frames": [
        {
          "frame_index": 1,
          "module": "vmsfdmff.dll",
          "function": "vmsfdmff.dll@0x5728",
          "file": "",
          "line": null,
          "raw": "1 \tvmsfdmff.dll \tvmsfdmff.dll@0x5728"
        },
        {
          "frame_index": 2,
          "module": "vmsfdmff.dll",
          "function": "vmsfdmff.dll@0x38f6",
          "file": "",
          "line": null,
          "raw": "2 \tvmsfdmff.dll \tvmsfdmff.dll@0x38f6"
        },
        {
          "frame_index": 3,
          "module": "vmsfdmff.dll",
          "function": "vmsfdmff.dll@0x3f69",
          "file": "",
          "line": null,
          "raw": "3 \tvmsfdmff.dll \tvmsfdmff.dll@0x3f69"
        },
        {
          "frame_index": 4,
          "module": "xul.dll",
          "function": "NS_InvokeByIndex_P",
          "file": "xpcom/reflect/xptcall/src/md/win32/xptcinvoke.cpp",
          "line": 70,
          "raw": "4 \txul.dll \tNS_InvokeByIndex_P \txpcom/reflect/xptcall/src/md/win32/xptcinvoke.cpp:70"
        },
        {
          "frame_index": 5,
          "module": "xul.dll",
          "function": "XPCWrappedNative::CallMethod",
          "file": "js/xpconnect/src/XPCWrappedNative.cpp",
          "line": 2442,
          "raw": "5 \txul.dll \tXPCWrappedNative::CallMethod \tjs/xpconnect/src/XPCWrappedNative.cpp:2442"
        },
        {
          "frame_index": 6,
          "module": "xul.dll",
          "function": "XPC_WN_CallMethod",
          "file": "js/xpconnect/src/XPCWrappedNativeJSOps.cpp",
          "line": 1500,
          "raw": "6 \txul.dll \tXPC_WN_CallMethod \tjs/xpconnect/src/XPCWrappedNativeJSOps.cpp:1500"
        },
        {
          "frame_index": 7,
          "module": "mozjs.dll",
          "function": "js::InvokeKernel",
          "file": "js/src/jsinterp.cpp",
          "line": 313,
          "raw": "7 \tmozjs.dll \tjs::InvokeKernel \tjs/src/jsinterp.cpp:313"
        },
        {
          "frame_index": 8,
          "module": "mozjs.dll",
          "function": "js::Interpret",
          "file": "js/src/jsinterp.cpp",
          "line": 2515,
          "raw": "8 \tmozjs.dll \tjs::Interpret \tjs/src/jsinterp.cpp:2515"
        },
        {
          "frame_index": 9,
          "module": "mozjs.dll",
          "function": "js::InvokeKernel",
          "file": "js/src/jsinterp.cpp",
          "line": 329,
          "raw": "9 \tmozjs.dll \tjs::InvokeKernel \tjs/src/jsinterp.cpp:329"
        },
        {
          "frame_index": 10,
          "module": "mozjs.dll",
          "function": "js::Invoke",
          "file": "js/src/jsinterp.cpp",
          "line": 361,
          "raw": "10 \tmozjs.dll \tjs::Invoke \tjs/src/jsinterp.cpp:361"
        },
        {
          "frame_index": 11,
          "module": "mozjs.dll",
          "function": "JS_CallFunctionValue",
          "file": "js/src/jsapi.cpp",
          "line": 5549,
          "raw": "11 \tmozjs.dll \tJS_CallFunctionValue \tjs/src/jsapi.cpp:5549"
        },
        {
          "frame_index": 12,
          "module": "xul.dll",
          "function": "nsXPCWrappedJSClass::CallMethod",
          "file": "js/xpconnect/src/XPCWrappedJSClass.cpp",
          "line": 1474,
          "raw": "12 \txul.dll \tnsXPCWrappedJSClass::CallMethod \tjs/xpconnect/src/XPCWrappedJSClass.cpp:1474"
        },
        {
          "frame_index": 13,
          "module": "xul.dll",
          "function": "XPCVariant::`scalar deleting destructor'",
          "file": "",
          "line": null,
          "raw": "13 \txul.dll \tXPCVariant::`scalar deleting destructor'"
        },
        {
          "frame_index": 14,
          "module": "xul.dll",
          "function": "nsJSEventListener::HandleEvent",
          "file": "dom/src/events/nsJSEventListener.cpp",
          "line": 141,
          "raw": "14 \txul.dll \tnsJSEventListener::HandleEvent \tdom/src/events/nsJSEventListener.cpp:141"
        },
        {
          "frame_index": 15,
          "module": "xul.dll",
          "function": "nsEventListenerManager::HandleEventInternal",
          "file": "content/events/src/nsEventListenerManager.cpp",
          "line": 868,
          "raw": "15 \txul.dll \tnsEventListenerManager::HandleEventInternal \tcontent/events/src/nsEventListenerManager.cpp:868"
        },
        {
          "frame_index": 16,
          "module": "xul.dll",
          "function": "nsEventTargetChainItem::HandleEventTargetChain",
          "file": "content/events/src/nsEventDispatcher.cpp",
          "line": 317,
          "raw": "16 \txul.dll \tnsEventTargetChainItem::HandleEventTargetChain \tcontent/events/src/nsEventDispatcher.cpp:317"
        },
        {
          "frame_index": 17,
          "module": "xul.dll",
          "function": "nsEventDispatcher::Dispatch",
          "file": "content/events/src/nsEventDispatcher.cpp",
          "line": 643,
          "raw": "17 \txul.dll \tnsEventDispatcher::Dispatch \tcontent/events/src/nsEventDispatcher.cpp:643"
        },
        {
          "frame_index": 18,
          "module": "xul.dll",
          "function": "DocumentViewerImpl::LoadComplete",
          "file": "layout/base/nsDocumentViewer.cpp",
          "line": 1023,
          "raw": "18 \txul.dll \tDocumentViewerImpl::LoadComplete \tlayout/base/nsDocumentViewer.cpp:1023"
        },
        {
          "frame_index": 19,
          "module": "xul.dll",
          "function": "nsDocShell::EndPageLoad",
          "file": "docshell/base/nsDocShell.cpp",
          "line": 6239,
          "raw": "19 \txul.dll \tnsDocShell::EndPageLoad \tdocshell/base/nsDocShell.cpp:6239"
        }
      ],
      "frame_count": 19
    },
    {
      "comment_id": 6944500,
      "comment_count": 14,
      "creator": "alervdvcw@gmail.com",
      "creation_time": "2012-12-26T08:41:25Z",
      "raw_text": "HI!\n\nThis stack trace does not look good according to our MAP file:\n\n1 \tvmsfdmff.dll \tvmsfdmff.dll@0x5728 \t\n2 \tvmsfdmff.dll \tvmsfdmff.dll@0x38f6 \t\n3 \tvmsfdmff.dll \tvmsfdmff.dll@0x3f69 \n\n2nd and 3d - are OK, but the 1st one - something strange...\n\nBut we analyzed code related to (3) and (2) and fixed some potential crash bugs.\nWe plan to release the new version today or in a few days.",
      "matched_patterns": [
        "(?i)(crash|stack)\\s*(trace|dump|report)"
      ],
      "parsed_frames": [
        {
          "frame_index": 1,
          "module": "vmsfdmff.dll",
          "function": "vmsfdmff.dll@0x5728",
          "file": "",
          "line": null,
          "raw": "1 \tvmsfdmff.dll \tvmsfdmff.dll@0x5728"
        },
        {
          "frame_index": 2,
          "module": "vmsfdmff.dll",
          "function": "vmsfdmff.dll@0x38f6",
          "file": "",
          "line": null,
          "raw": "2 \tvmsfdmff.dll \tvmsfdmff.dll@0x38f6"
        },
        {
          "frame_index": 3,
          "module": "vmsfdmff.dll",
          "function": "vmsfdmff.dll@0x3f69",
          "file": "",
          "line": null,
          "raw": "3 \tvmsfdmff.dll \tvmsfdmff.dll@0x3f69"
        }
      ],
      "frame_count": 3
    }
  ],
  "has_stack_traces": true,
  "stack_trace_count": 2,
  "total_parsed_frames": 22
}