{
  "bug_id": "807923",
  "summary": "crash in browsemngr.dll@0x11a176 with Browser Manager 2.3.796.11 bundled with Babylon",
  "status": "RESOLVED",
  "resolution": "FIXED",
  "product": "Firefox",
  "component": "Extension Compatibility",
  "version": "16 Branch",
  "severity": "critical",
  "priority": "--",
  "creation_time": "2012-11-02T09:34:50Z",
  "last_change_time": "2013-02-04T21:24:31Z",
  "is_recent": false,
  "crash_signature_raw": "[@ browsemngr.dll@0x11a176]",
  "crash_signatures": [
    "browsemngr.dll@0x11a176"
  ],
  "keywords": [
    "crash"
  ],
  "regressed_by": [],
  "regressions": [],
  "bugzilla_url": "https://bugzilla.mozilla.org/show_bug.cgi?id=807923",
  "socorro_links": [],
  "socorro_crash_ids": [],
  "has_socorro_link": false,
  "has_direct_crash_id": false,
  "stack_traces": [
    {
      "comment_id": 6786594,
      "comment_count": 0,
      "creator": "scoobidiver@netcourrier.com",
      "creation_time": "2012-11-02T09:34:50Z",
      "raw_text": "It's similar to bug 782706 but at a lower volume (#389 top browser crasher in 16.0.2) and happens with the latest version of Browser Manager according to crash correlations:\n0% (2/8294) 2.2.630.40\n0% (5/8294) 2.2.643.41\n1% (51/8294) 2.3.762.17\n1% (43/8294) 2.3.765.24\n2% (129/8294) 2.3.787.43\n1% (116/8294) 2.3.796.11\n\nSignature \tbrowsemngr.dll@0x11a176 More Reports Search\nUUID\t39ef1c46-3a2e-4266-b0e5-7a2782121102\nDate Processed\t2012-11-02 09:10:32\nUptime\t0\nLast Crash\t2.5 days before submission\nInstall Age\t6.3 days since version was first installed.\nInstall Time\t2012-10-27 01:46:13\nProduct\tFirefox\nVersion\t16.0.2\nBuild ID\t20121024073032\nRelease Channel\trelease\nOS\tWindows NT\nOS Version\t5.1.2600 Service Pack 2\nBuild Architecture\tx86\nBuild Architecture Info\tGenuineIntel family 15 model 4 stepping 1\nCrash Reason\tUnhandled C++ Exception\nCrash Address\t0x7c81eb33\nProcessor Notes \tWARNING: JSON file missing Add-ons\nEMCheckCompatibility\tFalse\nTotal Virtual Memory\t2147352576\nAvailable Virtual Memory\t2047877120\nSystem Memory Use Percentage\t41\nAvailable Page File\t2522611712\nAvailable Physical Memory\t472944640\n\nFrame \tModule \tSignature \tSource\n0 \tkernel32.dll \tRaiseException \t\n1 \tbrowsemngr.dll \tbrowsemngr.dll@0x11a176 \t\n2 \tbrowsemngr.dll \tbrowsemngr.dll@0x10f6 \t\n3 \tbrowsemngr.dll \tbrowsemngr.dll@0x1e4af \t\n4 \tbrowsemngr.dll \tbrowsemngr.dll@0x8aaf0 \t\n5 \tbrowsemngr.dll \tbrowsemngr.dll@0x1deaf \t\n6 \tbrowsemngr.dll \tbrowsemngr.dll@0x1e3fa \t\n7 \tbrowsemngr.dll \tbrowsemngr.dll@0x9317 \t\n8 \tkernel32.dll \tCreateFileW \t\n9 \txul.dll \tOpenFile \txpcom/io/nsLocalFileWin.cpp:636\n10 \txul.dll \tnsLocalFile::OpenNSPRFileDesc \txpcom/io/nsLocalFileWin.cpp:1203\n11 \txul.dll \tnsFileStreamBase::DoOpen \tnetwerk/base/src/nsFileStreams.cpp:292\n12 \txul.dll \tnsFileStreamBase::MaybeOpen \tnetwerk/base/src/nsFileStreams.cpp:276\n13 \txul.dll \tnsFileInputStream::Open \tnetwerk/base/src/nsFileStreams.cpp:366\n14 \txul.dll \tnsFileInputStream::Init \tnetwerk/base/src/nsFileStreams.cpp:398\n15 \txul.dll \tNS_NewLocalFileInputStream \tobj-firefox/dist/include/nsNetUtil.h:920\n16 \txul.dll \tmozilla::openPrefFile \tmodules/libpref/src/Preferences.cpp:762\n17 \txul.dll \tmozilla::Preferences::ReadAndOwnUserPrefFile \tmodules/libpref/src/Preferences.cpp:639\n18 \txul.dll \tmozilla::Preferences::UseDefaultPrefFile \tmodules/libpref/src/Preferences.cpp:563\n19 \txul.dll \tmozilla::Preferences::ReadUserPrefs \tmodules/libpref/src/Preferences.cpp:373\n20 \txul.dll \tmozilla::Preferences::ResetAndReadUserPrefs \tmodules/libpref/src/Preferences.cpp:331\n21 \txul.dll \tnsXREDirProvider::DoStartup \ttoolkit/xre/nsXREDirProvider.cpp:739\n22 \txul.dll \tXREMain::XRE_mainRun \ttoolkit/xre/nsAppRunner.cpp:3672\n23 \txul.dll \tXREMain::XRE_main \ttoolkit/xre/nsAppRunner.cpp:3871\n24 \txul.dll \tXRE_main \ttoolkit/xre/nsAppRunner.cpp:3947\n25 \tfirefox.exe \twmain \ttoolkit/xre/nsWindowsWMain.cpp:100\n26 \tfirefox.exe \t__tmainCRTStartup \tcrtexe.c:552\n27 \tkernel32.dll \tBaseProcessStart\n\nbrowsemngr.dll \t2.3.796.11 \t4D2D40DB7EC7427188EC3296ABD6B89A2 \tprotector.pdb\n\nhttps://crash-stats.mozilla.com/report/list?signature=browsemngr.dll%400x11a176",
      "matched_patterns": [
        "ns[A-Z]\\w+::\\w+"
      ],
      "parsed_frames": [
        {
          "frame_index": 0,
          "module": "kernel32.dll",
          "function": "RaiseException",
          "file": "",
          "line": null,
          "raw": "0 \tkernel32.dll \tRaiseException"
        },
        {
          "frame_index": 1,
          "module": "browsemngr.dll",
          "function": "browsemngr.dll@0x11a176",
          "file": "",
          "line": null,
          "raw": "1 \tbrowsemngr.dll \tbrowsemngr.dll@0x11a176"
        },
        {
          "frame_index": 2,
          "module": "browsemngr.dll",
          "function": "browsemngr.dll@0x10f6",
          "file": "",
          "line": null,
          "raw": "2 \tbrowsemngr.dll \tbrowsemngr.dll@0x10f6"
        },
        {
          "frame_index": 3,
          "module": "browsemngr.dll",
          "function": "browsemngr.dll@0x1e4af",
          "file": "",
          "line": null,
          "raw": "3 \tbrowsemngr.dll \tbrowsemngr.dll@0x1e4af"
        },
        {
          "frame_index": 4,
          "module": "browsemngr.dll",
          "function": "browsemngr.dll@0x8aaf0",
          "file": "",
          "line": null,
          "raw": "4 \tbrowsemngr.dll \tbrowsemngr.dll@0x8aaf0"
        },
        {
          "frame_index": 5,
          "module": "browsemngr.dll",
          "function": "browsemngr.dll@0x1deaf",
          "file": "",
          "line": null,
          "raw": "5 \tbrowsemngr.dll \tbrowsemngr.dll@0x1deaf"
        },
        {
          "frame_index": 6,
          "module": "browsemngr.dll",
          "function": "browsemngr.dll@0x1e3fa",
          "file": "",
          "line": null,
          "raw": "6 \tbrowsemngr.dll \tbrowsemngr.dll@0x1e3fa"
        },
        {
          "frame_index": 7,
          "module": "browsemngr.dll",
          "function": "browsemngr.dll@0x9317",
          "file": "",
          "line": null,
          "raw": "7 \tbrowsemngr.dll \tbrowsemngr.dll@0x9317"
        },
        {
          "frame_index": 8,
          "module": "kernel32.dll",
          "function": "CreateFileW",
          "file": "",
          "line": null,
          "raw": "8 \tkernel32.dll \tCreateFileW"
        },
        {
          "frame_index": 9,
          "module": "xul.dll",
          "function": "OpenFile",
          "file": "xpcom/io/nsLocalFileWin.cpp",
          "line": 636,
          "raw": "9 \txul.dll \tOpenFile \txpcom/io/nsLocalFileWin.cpp:636"
        },
        {
          "frame_index": 10,
          "module": "xul.dll",
          "function": "nsLocalFile::OpenNSPRFileDesc",
          "file": "xpcom/io/nsLocalFileWin.cpp",
          "line": 1203,
          "raw": "10 \txul.dll \tnsLocalFile::OpenNSPRFileDesc \txpcom/io/nsLocalFileWin.cpp:1203"
        },
        {
          "frame_index": 11,
          "module": "xul.dll",
          "function": "nsFileStreamBase::DoOpen",
          "file": "netwerk/base/src/nsFileStreams.cpp",
          "line": 292,
          "raw": "11 \txul.dll \tnsFileStreamBase::DoOpen \tnetwerk/base/src/nsFileStreams.cpp:292"
        },
        {
          "frame_index": 12,
          "module": "xul.dll",
          "function": "nsFileStreamBase::MaybeOpen",
          "file": "netwerk/base/src/nsFileStreams.cpp",
          "line": 276,
          "raw": "12 \txul.dll \tnsFileStreamBase::MaybeOpen \tnetwerk/base/src/nsFileStreams.cpp:276"
        },
        {
          "frame_index": 13,
          "module": "xul.dll",
          "function": "nsFileInputStream::Open",
          "file": "netwerk/base/src/nsFileStreams.cpp",
          "line": 366,
          "raw": "13 \txul.dll \tnsFileInputStream::Open \tnetwerk/base/src/nsFileStreams.cpp:366"
        },
        {
          "frame_index": 14,
          "module": "xul.dll",
          "function": "nsFileInputStream::Init",
          "file": "netwerk/base/src/nsFileStreams.cpp",
          "line": 398,
          "raw": "14 \txul.dll \tnsFileInputStream::Init \tnetwerk/base/src/nsFileStreams.cpp:398"
        },
        {
          "frame_index": 15,
          "module": "xul.dll",
          "function": "NS_NewLocalFileInputStream",
          "file": "obj-firefox/dist/include/nsNetUtil.h",
          "line": 920,
          "raw": "15 \txul.dll \tNS_NewLocalFileInputStream \tobj-firefox/dist/include/nsNetUtil.h:920"
        },
        {
          "frame_index": 16,
          "module": "xul.dll",
          "function": "mozilla::openPrefFile",
          "file": "modules/libpref/src/Preferences.cpp",
          "line": 762,
          "raw": "16 \txul.dll \tmozilla::openPrefFile \tmodules/libpref/src/Preferences.cpp:762"
        },
        {
          "frame_index": 17,
          "module": "xul.dll",
          "function": "mozilla::Preferences::ReadAndOwnUserPrefFile",
          "file": "modules/libpref/src/Preferences.cpp",
          "line": 639,
          "raw": "17 \txul.dll \tmozilla::Preferences::ReadAndOwnUserPrefFile \tmodules/libpref/src/Preferences.cpp:639"
        },
        {
          "frame_index": 18,
          "module": "xul.dll",
          "function": "mozilla::Preferences::UseDefaultPrefFile",
          "file": "modules/libpref/src/Preferences.cpp",
          "line": 563,
          "raw": "18 \txul.dll \tmozilla::Preferences::UseDefaultPrefFile \tmodules/libpref/src/Preferences.cpp:563"
        },
        {
          "frame_index": 19,
          "module": "xul.dll",
          "function": "mozilla::Preferences::ReadUserPrefs",
          "file": "modules/libpref/src/Preferences.cpp",
          "line": 373,
          "raw": "19 \txul.dll \tmozilla::Preferences::ReadUserPrefs \tmodules/libpref/src/Preferences.cpp:373"
        },
        {
          "frame_index": 20,
          "module": "xul.dll",
          "function": "mozilla::Preferences::ResetAndReadUserPrefs",
          "file": "modules/libpref/src/Preferences.cpp",
          "line": 331,
          "raw": "20 \txul.dll \tmozilla::Preferences::ResetAndReadUserPrefs \tmodules/libpref/src/Preferences.cpp:331"
        },
        {
          "frame_index": 21,
          "module": "xul.dll",
          "function": "nsXREDirProvider::DoStartup",
          "file": "toolkit/xre/nsXREDirProvider.cpp",
          "line": 739,
          "raw": "21 \txul.dll \tnsXREDirProvider::DoStartup \ttoolkit/xre/nsXREDirProvider.cpp:739"
        },
        {
          "frame_index": 22,
          "module": "xul.dll",
          "function": "XREMain::XRE_mainRun",
          "file": "toolkit/xre/nsAppRunner.cpp",
          "line": 3672,
          "raw": "22 \txul.dll \tXREMain::XRE_mainRun \ttoolkit/xre/nsAppRunner.cpp:3672"
        },
        {
          "frame_index": 23,
          "module": "xul.dll",
          "function": "XREMain::XRE_main",
          "file": "toolkit/xre/nsAppRunner.cpp",
          "line": 3871,
          "raw": "23 \txul.dll \tXREMain::XRE_main \ttoolkit/xre/nsAppRunner.cpp:3871"
        },
        {
          "frame_index": 24,
          "module": "xul.dll",
          "function": "XRE_main",
          "file": "toolkit/xre/nsAppRunner.cpp",
          "line": 3947,
          "raw": "24 \txul.dll \tXRE_main \ttoolkit/xre/nsAppRunner.cpp:3947"
        },
        {
          "frame_index": 27,
          "module": "kernel32.dll",
          "function": "BaseProcessStart",
          "file": "",
          "line": null,
          "raw": "27 \tkernel32.dll \tBaseProcessStart"
        }
      ],
      "frame_count": 26
    }
  ],
  "has_stack_traces": true,
  "stack_trace_count": 1,
  "total_parsed_frames": 26
}