{
  "bug_id": "711935",
  "summary": "Crash in XPC_WN_GetterSetter @ msvcr80.dll@0x14500 while dragging a tab with TorButton 1.4.5",
  "status": "RESOLVED",
  "resolution": "FIXED",
  "product": "Firefox",
  "component": "Extension Compatibility",
  "version": "9 Branch",
  "severity": "critical",
  "priority": "--",
  "creation_time": "2011-12-19T11:07:06Z",
  "last_change_time": "2012-02-10T06:48:27Z",
  "is_recent": false,
  "crash_signature_raw": "[@ msvcr80.dll@0x14500]",
  "crash_signatures": [
    "msvcr80.dll@0x14500"
  ],
  "keywords": [
    "crash",
    "topcrash"
  ],
  "regressed_by": [],
  "regressions": [],
  "bugzilla_url": "https://bugzilla.mozilla.org/show_bug.cgi?id=711935",
  "socorro_links": [],
  "socorro_crash_ids": [],
  "has_socorro_link": false,
  "has_direct_crash_id": false,
  "stack_traces": [
    {
      "comment_id": 5926294,
      "comment_count": 0,
      "creator": "scoobidiver@netcourrier.com",
      "creation_time": "2011-12-19T11:07:06Z",
      "raw_text": "It's #10 crasher in 9.0b6 and first appeared with that stack trace around December 14th.\n\nIt has been hidden behind bug 700302 and its dupe. msvcr80.dll should have been added to the Socorro skiplist in order to not miss it.\n\nAll comments talk about dragging a tab.\n\nIt's correlated to TorButton:\n    100% (147/147) vs.   1% (178/28968) {e0204bd5-9d31-402b-a99d-a6aa8ffebdca} (Torbutton, https://addons.mozilla.org/addon/2275)\n          0% (0/147) vs.   0% (1/28968) 1.4.4.1\n        100% (147/147) vs.   1% (173/28968) 1.4.5\n          0% (0/147) vs.   0% (4/28968) 1.4.5.1\n\nIt's fixed in TorButton 1.4.5.1:\nhttps://gitweb.torproject.org/torbutton.git/blob/HEAD:/src/CHANGELOG\n\nSignature \tmsvcr80.dll@0x14500 More Reports Search\nUUID\t353c65a1-d50d-4b83-8d7d-93f0d2111218\nDate Processed\t2011-12-18 04:42:04.779641\nUptime\t148\nLast Crash\t4.8 hours before submission\nInstall Age\t3.1 weeks since version was first installed.\nInstall Time\t2011-11-26 19:08:43\nProduct\tFirefox\nVersion\t9.0\nBuild ID\t20111122192043\nRelease Channel\tbeta\nOS\tWindows NT\nOS Version\t6.1.7601 Service Pack 1\nBuild Architecture\tx86\nBuild Architecture Info\tGenuineIntel family 6 model 23 stepping 10\nCrash Reason\tEXCEPTION_ACCESS_VIOLATION_READ\nCrash Address\t0xffffffff989dbfa0\nApp Notes \tAdapterVendorID: 1002, AdapterDeviceID: 9480, AdapterSubsysID: 3624103c, AdapterDriverVersion: 8.632.0.0\nD3D10 Layers? D3D10 Layers-\nD3D9 Layers? D3D9 Layers-\nEMCheckCompatibility\tTrue\n\nFrame \tModule \tSignature [Expand] \tSource\n0 \tmsvcr80.dll \tmsvcr80.dll@0x14500 \t\n1 \txul.dll \tXPC_WN_GetterSetter \tjs/src/xpconnect/src/xpcwrappednativejsops.cpp:1679\n2 \tmozjs.dll \tjs::InvokeKernel \tjs/src/jsinterp.cpp:660\n3 \tmozjs.dll \tjs::Invoke \tjs/src/jsinterp.cpp:710\n4 \tmozjs.dll \tjs::InvokeGetterOrSetter \tjs/src/jsinterp.cpp:747\n5 \tmozjs.dll \tjs::Shape::get \tjs/src/jsscopeinlines.h:279\n6 \tmozjs.dll \tjs_GetPropertyHelper \tjs/src/jsobj.cpp:5930\n7 \tmozjs.dll \tjs::Interpret \tjs/src/jsinterp.cpp:3564\n8 \tmozjs.dll \tjs::types::TypeMonitorCall \tjs/src/jsinferinlines.h:327\n9 \tmozjs.dll \tUncachedInlineCall \tjs/src/methodjit/InvokeHelpers.cpp:393\n10 \tmozjs.dll \tjs::mjit::stubs::UncachedCallHelper \tjs/src/methodjit/InvokeHelpers.cpp:480\n11 \tmozjs.dll \tCallCompiler::update \tjs/src/methodjit/MonoIC.cpp:1088\n12 \tmozjs.dll \tjs::mjit::ic::Call \tjs/src/methodjit/MonoIC.cpp:1148\n13 \tmozjs.dll \tjs::mjit::EnterMethodJIT \tjs/src/methodjit/MethodJIT.cpp:884\n14 \tmozjs.dll \tjs::mjit::JaegerShot \tjs/src/methodjit/MethodJIT.cpp:962\n15 \tmozjs.dll \tjs::RunScript \tjs/src/jsinterp.cpp:611\n16 \tmozjs.dll \tjs::InvokeKernel \tjs/src/jsinterp.cpp:678\n17 \tmozjs.dll \tjs::Invoke \tjs/src/jsinterp.cpp:710\n18 \tmozjs.dll \tJS_CallFunctionValue \tjs/src/jsapi.cpp:5039\n19 \txul.dll \tnsXPCWrappedJSClass::CallMethod \tjs/src/xpconnect/src/xpcwrappedjsclass.cpp:1660\n20 \txul.dll \tnsXPCWrappedJS::CallMethod \tjs/src/xpconnect/src/xpcwrappedjs.cpp:585\n21 \txul.dll \tPrepareAndDispatch \txpcom/reflect/xptcall/src/md/win32/xptcstubs.cpp:114\n22 \txul.dll \tSharedStub \txpcom/reflect/xptcall/src/md/win32/xptcstubs.cpp:141\n23 \txul.dll \tnsEventListenerManager::HandleEventInternal \tcontent/events/src/nsEventListenerManager.cpp:778\n24 \txul.dll \tnsEventTargetChainItem::HandleEventTargetChain \tcontent/events/src/nsEventDispatcher.cpp:314\n25 \txul.dll \tnsEventDispatcher::Dispatch \tcontent/events/src/nsEventDispatcher.cpp:672\n26 \txul.dll \tPresShell::HandleEventInternal \tlayout/base/nsPresShell.cpp:6346\n27 \txul.dll \tPresShell::HandlePositionedEvent \tlayout/base/nsPresShell.cpp:6132\n28 \txul.dll \tPresShell::HandleEvent \tlayout/base/nsPresShell.cpp:5967\n29 \txul.dll \tnsViewManager::HandleEvent \tview/src/nsViewManager.cpp:1029\n30 \txul.dll \tnsViewManager::DispatchEvent \tview/src/nsViewManager.cpp:1007\n31 \txul.dll \tAttachedHandleEvent \tview/src/nsView.cpp:191\n32 \txul.dll \tnsWindow::DispatchEvent \twidget/src/windows/nsWindow.cpp:3580\n33 \txul.dll \tnsNativeDragTarget::DispatchDragDropEvent \twidget/src/windows/nsNativeDragTarget.cpp:205\n34 \txul.dll \tnsNativeDragTarget::ProcessDrag \twidget/src/windows/nsNativeDragTarget.cpp:228\n35 \txul.dll \tnsNativeDragTarget::DragOver \twidget/src/windows/nsNativeDragTarget.cpp:346\n36 \tole32.dll \tCPrivDragDrop::PrivDragDrop \t\n37 \tole32.dll \tPrivDragDrop \t\n38 \tole32.dll \tCDropTarget::DragOver \t\n39 \tole32.dll \tCDragOperation::DragOver \t\n40 \tole32.dll \tDoDragDrop \t\n41 \txul.dll \tnsDragService::StartInvokingDragSession \twidget/src/windows/nsDragService.cpp:317\n42 \txul.dll \tnsDragService::InvokeDragSession \twidget/src/windows/nsDragService.cpp:267\n43 \txul.dll \tnsBaseDragService::InvokeDragSessionWithImage \twidget/src/xpwidgets/nsBaseDragService.cpp:286\n44 \txul.dll \tNS_InvokeByIndex_P \txpcom/reflect/xptcall/src/md/win32/xptcinvoke.cpp:102\n45 \txul.dll \tXPC_WN_CallMethod \tjs/src/xpconnect/src/xpcwrappednativejsops.cpp:1629\n46 \tmozjs.dll \tjs::InvokeKernel \tjs/src/jsinterp.cpp:660\n47 \tmozjs.dll \tjs::Interpret \tjs/src/jsinterp.cpp:4036\n48 \tmozjs.dll \tjs::analyze::ScriptAnalysis::integerOperation \tjs/src/jsinfer.cpp:4327\n49 \tmozjs.dll \tjs::RunScript \tjs/src/jsinterp.cpp:614\n50 \tmozjs.dll \tjs::InvokeKernel \tjs/src/jsinterp.cpp:678\n51 \tmozjs.dll \tjs::Invoke \tjs/src/jsinterp.cpp:710\n52 \tmozjs.dll \tJS_CallFunctionValue \tjs/src/jsapi.cpp:5039\n53 \txul.dll \tnsXPCWrappedJSClass::CallMethod \tjs/src/xpconnect/src/xpcwrappedjsclass.cpp:1660\n54 \txul.dll \tnsXPCWrappedJS::CallMethod \tjs/src/xpconnect/src/xpcwrappedjs.cpp:585\n55 \txul.dll \tPrepareAndDispatch \txpcom/reflect/xptcall/src/md/win32/xptcstubs.cpp:114\n56 \txul.dll \tSharedStub \txpcom/reflect/xptcall/src/md/win32/xptcstubs.cpp:141\n57 \txul.dll \tnsEventStateManager::DoDefaultDragStart \tcontent/events/src/nsEventStateManager.cpp:2392\n\nMore reports at:\nhttps://crash-stats.mozilla.com/report/list?version=Firefox:9.0b6&signature=msvcr80.dll%400x14500",
      "matched_patterns": [
        "ns[A-Z]\\w+::\\w+",
        "(?i)(crash|stack)\\s*(trace|dump|report)"
      ],
      "parsed_frames": [
        {
          "frame_index": 0,
          "module": "msvcr80.dll",
          "function": "msvcr80.dll@0x14500",
          "file": "",
          "line": null,
          "raw": "0 \tmsvcr80.dll \tmsvcr80.dll@0x14500"
        },
        {
          "frame_index": 1,
          "module": "xul.dll",
          "function": "XPC_WN_GetterSetter",
          "file": "js/src/xpconnect/src/xpcwrappednativejsops.cpp",
          "line": 1679,
          "raw": "1 \txul.dll \tXPC_WN_GetterSetter \tjs/src/xpconnect/src/xpcwrappednativejsops.cpp:1679"
        },
        {
          "frame_index": 2,
          "module": "mozjs.dll",
          "function": "js::InvokeKernel",
          "file": "js/src/jsinterp.cpp",
          "line": 660,
          "raw": "2 \tmozjs.dll \tjs::InvokeKernel \tjs/src/jsinterp.cpp:660"
        },
        {
          "frame_index": 3,
          "module": "mozjs.dll",
          "function": "js::Invoke",
          "file": "js/src/jsinterp.cpp",
          "line": 710,
          "raw": "3 \tmozjs.dll \tjs::Invoke \tjs/src/jsinterp.cpp:710"
        },
        {
          "frame_index": 4,
          "module": "mozjs.dll",
          "function": "js::InvokeGetterOrSetter",
          "file": "js/src/jsinterp.cpp",
          "line": 747,
          "raw": "4 \tmozjs.dll \tjs::InvokeGetterOrSetter \tjs/src/jsinterp.cpp:747"
        },
        {
          "frame_index": 5,
          "module": "mozjs.dll",
          "function": "js::Shape::get",
          "file": "js/src/jsscopeinlines.h",
          "line": 279,
          "raw": "5 \tmozjs.dll \tjs::Shape::get \tjs/src/jsscopeinlines.h:279"
        },
        {
          "frame_index": 6,
          "module": "mozjs.dll",
          "function": "js_GetPropertyHelper",
          "file": "js/src/jsobj.cpp",
          "line": 5930,
          "raw": "6 \tmozjs.dll \tjs_GetPropertyHelper \tjs/src/jsobj.cpp:5930"
        },
        {
          "frame_index": 7,
          "module": "mozjs.dll",
          "function": "js::Interpret",
          "file": "js/src/jsinterp.cpp",
          "line": 3564,
          "raw": "7 \tmozjs.dll \tjs::Interpret \tjs/src/jsinterp.cpp:3564"
        },
        {
          "frame_index": 8,
          "module": "mozjs.dll",
          "function": "js::types::TypeMonitorCall",
          "file": "js/src/jsinferinlines.h",
          "line": 327,
          "raw": "8 \tmozjs.dll \tjs::types::TypeMonitorCall \tjs/src/jsinferinlines.h:327"
        },
        {
          "frame_index": 9,
          "module": "mozjs.dll",
          "function": "UncachedInlineCall",
          "file": "js/src/methodjit/InvokeHelpers.cpp",
          "line": 393,
          "raw": "9 \tmozjs.dll \tUncachedInlineCall \tjs/src/methodjit/InvokeHelpers.cpp:393"
        },
        {
          "frame_index": 10,
          "module": "mozjs.dll",
          "function": "js::mjit::stubs::UncachedCallHelper",
          "file": "js/src/methodjit/InvokeHelpers.cpp",
          "line": 480,
          "raw": "10 \tmozjs.dll \tjs::mjit::stubs::UncachedCallHelper \tjs/src/methodjit/InvokeHelpers.cpp:480"
        },
        {
          "frame_index": 11,
          "module": "mozjs.dll",
          "function": "CallCompiler::update",
          "file": "js/src/methodjit/MonoIC.cpp",
          "line": 1088,
          "raw": "11 \tmozjs.dll \tCallCompiler::update \tjs/src/methodjit/MonoIC.cpp:1088"
        },
        {
          "frame_index": 12,
          "module": "mozjs.dll",
          "function": "js::mjit::ic::Call",
          "file": "js/src/methodjit/MonoIC.cpp",
          "line": 1148,
          "raw": "12 \tmozjs.dll \tjs::mjit::ic::Call \tjs/src/methodjit/MonoIC.cpp:1148"
        },
        {
          "frame_index": 13,
          "module": "mozjs.dll",
          "function": "js::mjit::EnterMethodJIT",
          "file": "js/src/methodjit/MethodJIT.cpp",
          "line": 884,
          "raw": "13 \tmozjs.dll \tjs::mjit::EnterMethodJIT \tjs/src/methodjit/MethodJIT.cpp:884"
        },
        {
          "frame_index": 14,
          "module": "mozjs.dll",
          "function": "js::mjit::JaegerShot",
          "file": "js/src/methodjit/MethodJIT.cpp",
          "line": 962,
          "raw": "14 \tmozjs.dll \tjs::mjit::JaegerShot \tjs/src/methodjit/MethodJIT.cpp:962"
        },
        {
          "frame_index": 15,
          "module": "mozjs.dll",
          "function": "js::RunScript",
          "file": "js/src/jsinterp.cpp",
          "line": 611,
          "raw": "15 \tmozjs.dll \tjs::RunScript \tjs/src/jsinterp.cpp:611"
        },
        {
          "frame_index": 16,
          "module": "mozjs.dll",
          "function": "js::InvokeKernel",
          "file": "js/src/jsinterp.cpp",
          "line": 678,
          "raw": "16 \tmozjs.dll \tjs::InvokeKernel \tjs/src/jsinterp.cpp:678"
        },
        {
          "frame_index": 17,
          "module": "mozjs.dll",
          "function": "js::Invoke",
          "file": "js/src/jsinterp.cpp",
          "line": 710,
          "raw": "17 \tmozjs.dll \tjs::Invoke \tjs/src/jsinterp.cpp:710"
        },
        {
          "frame_index": 18,
          "module": "mozjs.dll",
          "function": "JS_CallFunctionValue",
          "file": "js/src/jsapi.cpp",
          "line": 5039,
          "raw": "18 \tmozjs.dll \tJS_CallFunctionValue \tjs/src/jsapi.cpp:5039"
        },
        {
          "frame_index": 19,
          "module": "xul.dll",
          "function": "nsXPCWrappedJSClass::CallMethod",
          "file": "js/src/xpconnect/src/xpcwrappedjsclass.cpp",
          "line": 1660,
          "raw": "19 \txul.dll \tnsXPCWrappedJSClass::CallMethod \tjs/src/xpconnect/src/xpcwrappedjsclass.cpp:1660"
        },
        {
          "frame_index": 20,
          "module": "xul.dll",
          "function": "nsXPCWrappedJS::CallMethod",
          "file": "js/src/xpconnect/src/xpcwrappedjs.cpp",
          "line": 585,
          "raw": "20 \txul.dll \tnsXPCWrappedJS::CallMethod \tjs/src/xpconnect/src/xpcwrappedjs.cpp:585"
        },
        {
          "frame_index": 21,
          "module": "xul.dll",
          "function": "PrepareAndDispatch",
          "file": "xpcom/reflect/xptcall/src/md/win32/xptcstubs.cpp",
          "line": 114,
          "raw": "21 \txul.dll \tPrepareAndDispatch \txpcom/reflect/xptcall/src/md/win32/xptcstubs.cpp:114"
        },
        {
          "frame_index": 22,
          "module": "xul.dll",
          "function": "SharedStub",
          "file": "xpcom/reflect/xptcall/src/md/win32/xptcstubs.cpp",
          "line": 141,
          "raw": "22 \txul.dll \tSharedStub \txpcom/reflect/xptcall/src/md/win32/xptcstubs.cpp:141"
        },
        {
          "frame_index": 23,
          "module": "xul.dll",
          "function": "nsEventListenerManager::HandleEventInternal",
          "file": "content/events/src/nsEventListenerManager.cpp",
          "line": 778,
          "raw": "23 \txul.dll \tnsEventListenerManager::HandleEventInternal \tcontent/events/src/nsEventListenerManager.cpp:778"
        },
        {
          "frame_index": 24,
          "module": "xul.dll",
          "function": "nsEventTargetChainItem::HandleEventTargetChain",
          "file": "content/events/src/nsEventDispatcher.cpp",
          "line": 314,
          "raw": "24 \txul.dll \tnsEventTargetChainItem::HandleEventTargetChain \tcontent/events/src/nsEventDispatcher.cpp:314"
        },
        {
          "frame_index": 25,
          "module": "xul.dll",
          "function": "nsEventDispatcher::Dispatch",
          "file": "content/events/src/nsEventDispatcher.cpp",
          "line": 672,
          "raw": "25 \txul.dll \tnsEventDispatcher::Dispatch \tcontent/events/src/nsEventDispatcher.cpp:672"
        },
        {
          "frame_index": 26,
          "module": "xul.dll",
          "function": "PresShell::HandleEventInternal",
          "file": "layout/base/nsPresShell.cpp",
          "line": 6346,
          "raw": "26 \txul.dll \tPresShell::HandleEventInternal \tlayout/base/nsPresShell.cpp:6346"
        },
        {
          "frame_index": 27,
          "module": "xul.dll",
          "function": "PresShell::HandlePositionedEvent",
          "file": "layout/base/nsPresShell.cpp",
          "line": 6132,
          "raw": "27 \txul.dll \tPresShell::HandlePositionedEvent \tlayout/base/nsPresShell.cpp:6132"
        },
        {
          "frame_index": 28,
          "module": "xul.dll",
          "function": "PresShell::HandleEvent",
          "file": "layout/base/nsPresShell.cpp",
          "line": 5967,
          "raw": "28 \txul.dll \tPresShell::HandleEvent \tlayout/base/nsPresShell.cpp:5967"
        },
        {
          "frame_index": 29,
          "module": "xul.dll",
          "function": "nsViewManager::HandleEvent",
          "file": "view/src/nsViewManager.cpp",
          "line": 1029,
          "raw": "29 \txul.dll \tnsViewManager::HandleEvent \tview/src/nsViewManager.cpp:1029"
        },
        {
          "frame_index": 30,
          "module": "xul.dll",
          "function": "nsViewManager::DispatchEvent",
          "file": "view/src/nsViewManager.cpp",
          "line": 1007,
          "raw": "30 \txul.dll \tnsViewManager::DispatchEvent \tview/src/nsViewManager.cpp:1007"
        },
        {
          "frame_index": 31,
          "module": "xul.dll",
          "function": "AttachedHandleEvent",
          "file": "view/src/nsView.cpp",
          "line": 191,
          "raw": "31 \txul.dll \tAttachedHandleEvent \tview/src/nsView.cpp:191"
        },
        {
          "frame_index": 32,
          "module": "xul.dll",
          "function": "nsWindow::DispatchEvent",
          "file": "widget/src/windows/nsWindow.cpp",
          "line": 3580,
          "raw": "32 \txul.dll \tnsWindow::DispatchEvent \twidget/src/windows/nsWindow.cpp:3580"
        },
        {
          "frame_index": 33,
          "module": "xul.dll",
          "function": "nsNativeDragTarget::DispatchDragDropEvent",
          "file": "widget/src/windows/nsNativeDragTarget.cpp",
          "line": 205,
          "raw": "33 \txul.dll \tnsNativeDragTarget::DispatchDragDropEvent \twidget/src/windows/nsNativeDragTarget.cpp:205"
        },
        {
          "frame_index": 34,
          "module": "xul.dll",
          "function": "nsNativeDragTarget::ProcessDrag",
          "file": "widget/src/windows/nsNativeDragTarget.cpp",
          "line": 228,
          "raw": "34 \txul.dll \tnsNativeDragTarget::ProcessDrag \twidget/src/windows/nsNativeDragTarget.cpp:228"
        },
        {
          "frame_index": 35,
          "module": "xul.dll",
          "function": "nsNativeDragTarget::DragOver",
          "file": "widget/src/windows/nsNativeDragTarget.cpp",
          "line": 346,
          "raw": "35 \txul.dll \tnsNativeDragTarget::DragOver \twidget/src/windows/nsNativeDragTarget.cpp:346"
        },
        {
          "frame_index": 36,
          "module": "ole32.dll",
          "function": "CPrivDragDrop::PrivDragDrop",
          "file": "",
          "line": null,
          "raw": "36 \tole32.dll \tCPrivDragDrop::PrivDragDrop"
        },
        {
          "frame_index": 37,
          "module": "ole32.dll",
          "function": "PrivDragDrop",
          "file": "",
          "line": null,
          "raw": "37 \tole32.dll \tPrivDragDrop"
        },
        {
          "frame_index": 38,
          "module": "ole32.dll",
          "function": "CDropTarget::DragOver",
          "file": "",
          "line": null,
          "raw": "38 \tole32.dll \tCDropTarget::DragOver"
        },
        {
          "frame_index": 39,
          "module": "ole32.dll",
          "function": "CDragOperation::DragOver",
          "file": "",
          "line": null,
          "raw": "39 \tole32.dll \tCDragOperation::DragOver"
        },
        {
          "frame_index": 40,
          "module": "ole32.dll",
          "function": "DoDragDrop",
          "file": "",
          "line": null,
          "raw": "40 \tole32.dll \tDoDragDrop"
        },
        {
          "frame_index": 41,
          "module": "xul.dll",
          "function": "nsDragService::StartInvokingDragSession",
          "file": "widget/src/windows/nsDragService.cpp",
          "line": 317,
          "raw": "41 \txul.dll \tnsDragService::StartInvokingDragSession \twidget/src/windows/nsDragService.cpp:317"
        },
        {
          "frame_index": 42,
          "module": "xul.dll",
          "function": "nsDragService::InvokeDragSession",
          "file": "widget/src/windows/nsDragService.cpp",
          "line": 267,
          "raw": "42 \txul.dll \tnsDragService::InvokeDragSession \twidget/src/windows/nsDragService.cpp:267"
        },
        {
          "frame_index": 43,
          "module": "xul.dll",
          "function": "nsBaseDragService::InvokeDragSessionWithImage",
          "file": "widget/src/xpwidgets/nsBaseDragService.cpp",
          "line": 286,
          "raw": "43 \txul.dll \tnsBaseDragService::InvokeDragSessionWithImage \twidget/src/xpwidgets/nsBaseDragService.cpp:286"
        },
        {
          "frame_index": 44,
          "module": "xul.dll",
          "function": "NS_InvokeByIndex_P",
          "file": "xpcom/reflect/xptcall/src/md/win32/xptcinvoke.cpp",
          "line": 102,
          "raw": "44 \txul.dll \tNS_InvokeByIndex_P \txpcom/reflect/xptcall/src/md/win32/xptcinvoke.cpp:102"
        },
        {
          "frame_index": 45,
          "module": "xul.dll",
          "function": "XPC_WN_CallMethod",
          "file": "js/src/xpconnect/src/xpcwrappednativejsops.cpp",
          "line": 1629,
          "raw": "45 \txul.dll \tXPC_WN_CallMethod \tjs/src/xpconnect/src/xpcwrappednativejsops.cpp:1629"
        },
        {
          "frame_index": 46,
          "module": "mozjs.dll",
          "function": "js::InvokeKernel",
          "file": "js/src/jsinterp.cpp",
          "line": 660,
          "raw": "46 \tmozjs.dll \tjs::InvokeKernel \tjs/src/jsinterp.cpp:660"
        },
        {
          "frame_index": 47,
          "module": "mozjs.dll",
          "function": "js::Interpret",
          "file": "js/src/jsinterp.cpp",
          "line": 4036,
          "raw": "47 \tmozjs.dll \tjs::Interpret \tjs/src/jsinterp.cpp:4036"
        },
        {
          "frame_index": 48,
          "module": "mozjs.dll",
          "function": "js::analyze::ScriptAnalysis::integerOperation",
          "file": "js/src/jsinfer.cpp",
          "line": 4327,
          "raw": "48 \tmozjs.dll \tjs::analyze::ScriptAnalysis::integerOperation \tjs/src/jsinfer.cpp:4327"
        },
        {
          "frame_index": 49,
          "module": "mozjs.dll",
          "function": "js::RunScript",
          "file": "js/src/jsinterp.cpp",
          "line": 614,
          "raw": "49 \tmozjs.dll \tjs::RunScript \tjs/src/jsinterp.cpp:614"
        },
        {
          "frame_index": 50,
          "module": "mozjs.dll",
          "function": "js::InvokeKernel",
          "file": "js/src/jsinterp.cpp",
          "line": 678,
          "raw": "50 \tmozjs.dll \tjs::InvokeKernel \tjs/src/jsinterp.cpp:678"
        },
        {
          "frame_index": 51,
          "module": "mozjs.dll",
          "function": "js::Invoke",
          "file": "js/src/jsinterp.cpp",
          "line": 710,
          "raw": "51 \tmozjs.dll \tjs::Invoke \tjs/src/jsinterp.cpp:710"
        },
        {
          "frame_index": 52,
          "module": "mozjs.dll",
          "function": "JS_CallFunctionValue",
          "file": "js/src/jsapi.cpp",
          "line": 5039,
          "raw": "52 \tmozjs.dll \tJS_CallFunctionValue \tjs/src/jsapi.cpp:5039"
        },
        {
          "frame_index": 53,
          "module": "xul.dll",
          "function": "nsXPCWrappedJSClass::CallMethod",
          "file": "js/src/xpconnect/src/xpcwrappedjsclass.cpp",
          "line": 1660,
          "raw": "53 \txul.dll \tnsXPCWrappedJSClass::CallMethod \tjs/src/xpconnect/src/xpcwrappedjsclass.cpp:1660"
        },
        {
          "frame_index": 54,
          "module": "xul.dll",
          "function": "nsXPCWrappedJS::CallMethod",
          "file": "js/src/xpconnect/src/xpcwrappedjs.cpp",
          "line": 585,
          "raw": "54 \txul.dll \tnsXPCWrappedJS::CallMethod \tjs/src/xpconnect/src/xpcwrappedjs.cpp:585"
        },
        {
          "frame_index": 55,
          "module": "xul.dll",
          "function": "PrepareAndDispatch",
          "file": "xpcom/reflect/xptcall/src/md/win32/xptcstubs.cpp",
          "line": 114,
          "raw": "55 \txul.dll \tPrepareAndDispatch \txpcom/reflect/xptcall/src/md/win32/xptcstubs.cpp:114"
        },
        {
          "frame_index": 56,
          "module": "xul.dll",
          "function": "SharedStub",
          "file": "xpcom/reflect/xptcall/src/md/win32/xptcstubs.cpp",
          "line": 141,
          "raw": "56 \txul.dll \tSharedStub \txpcom/reflect/xptcall/src/md/win32/xptcstubs.cpp:141"
        },
        {
          "frame_index": 57,
          "module": "xul.dll",
          "function": "nsEventStateManager::DoDefaultDragStart",
          "file": "content/events/src/nsEventStateManager.cpp",
          "line": 2392,
          "raw": "57 \txul.dll \tnsEventStateManager::DoDefaultDragStart \tcontent/events/src/nsEventStateManager.cpp:2392"
        }
      ],
      "frame_count": 58
    }
  ],
  "has_stack_traces": true,
  "stack_trace_count": 1,
  "total_parsed_frames": 58
}