{
  "bug_id": "840901",
  "summary": "crash in nsDocLoader::DoFireOnStateChange with Whitesky's ID Vault (bundled with HP computers?)",
  "status": "RESOLVED",
  "resolution": "FIXED",
  "product": "Firefox",
  "component": "Extension Compatibility",
  "version": "19 Branch",
  "severity": "critical",
  "priority": "--",
  "creation_time": "2013-02-13T08:49:30Z",
  "last_change_time": "2013-06-18T14:07:58Z",
  "is_recent": false,
  "crash_signature_raw": "[@ nsDocLoader::DoFireOnStateChange(nsIWebProgress* const, nsIRequest* const, int&, tag_nsresult)]\r\n[@ @0x0 | nsDocLoader::DoFireOnStateChange(nsIWebProgress* const, nsIRequest* const, int&, tag_nsresult) ]",
  "crash_signatures": [
    "nsDocLoader::DoFireOnStateChange(nsIWebProgress* const, nsIRequest* const, int&, tag_nsresult)",
    "@0x0 | nsDocLoader::DoFireOnStateChange(nsIWebProgress* const, nsIRequest* const, int&, tag_nsresult)"
  ],
  "keywords": [
    "crash",
    "steps-wanted",
    "thirdparty",
    "topcrash"
  ],
  "regressed_by": [],
  "regressions": [],
  "bugzilla_url": "https://bugzilla.mozilla.org/show_bug.cgi?id=840901",
  "socorro_links": [],
  "socorro_crash_ids": [],
  "has_socorro_link": false,
  "has_direct_crash_id": false,
  "stack_traces": [
    {
      "comment_id": 7098373,
      "comment_count": 0,
      "creator": "scoobidiver@netcourrier.com",
      "creation_time": "2013-02-13T08:49:30Z",
      "raw_text": "It's #5 top crasher in 18.0.2 for Windows 8 only.\n\nIt's correlated to CGPS Extension (ID Vault product from Whitesky - see http://www.idvault.com/):\n     96% (47/49) vs.   0% (542/137733) idvaultaddin@whitesky (CGPS Extension)\n          0% (0/49) vs.   0% (1/137733) 1.0\n          0% (0/49) vs.   0% (1/137733) 1.12.1127.2\n          0% (0/49) vs.   0% (433/137733) 1.13.111.1\n         96% (47/49) vs.   0% (107/137733) 1.13.111.2\n\nThat product likely comes bundled in some brand new computers (HP?).\n\nSignature \tnsDocLoader::DoFireOnStateChange(nsIWebProgress* const, nsIRequest* const, int&, tag_nsresult) More Reports Search\nUUID\tdace5c09-e5e0-45fa-b447-0b6ab2130213\nDate Processed\t2013-02-13 07:49:38\nUptime\t132\nLast Crash\t2.2 minutes before submission\nInstall Age\t1.0 weeks since version was first installed.\nInstall Time\t2013-02-06 02:09:38\nProduct\tFirefox\nVersion\t18.0.2\nBuild ID\t20130201065344\nRelease Channel\trelease\nOS\tWindows NT\nOS Version\t6.2.9200\nBuild Architecture\tx86\nBuild Architecture Info\tGenuineIntel family 6 model 58 stepping 9\nCrash Reason\tEXCEPTION_ACCESS_VIOLATION_EXEC\nCrash Address\t0xffffffffffffb991\nApp Notes \t\nAdapterVendorID: 0x10de, AdapterDeviceID: 0x0fc6, AdapterSubsysID: 00000000, AdapterDriverVersion: 9.18.13.1090\nD2D? D2D+ DWrite? DWrite+ D3D10 Layers? D3D10 Layers+ WebGL? EGL? EGL+ GL Context? GL Context+ WebGL+ \nProcessor Notes \tsp-processor09.phx1.mozilla.com_434:2008\nEMCheckCompatibility\tTrue\nAdapter Vendor ID\t0x10de\nAdapter Device ID\t0x0fc6\nTotal Virtual Memory\t4294836224\nAvailable Virtual Memory\t3403517952\nSystem Memory Use Percentage\t17\nAvailable Page File\t16058220544\nAvailable Physical Memory\t14175633408\n\nFrame \tModule \tSignature \tSource\n0 \t\t@0xffffb991 \t\n1 \t\t@0x8d5d540 \t\n2 \t\t@0xefc0fc1 \t\n3 \t\t@0x87f84db \t\n4 \t\t@0x8d5f334 \t\n5 \t\t@0x8d5f16c \t\n6 \t\t@0x87f83f8 \t\n7 \txul.dll \tnsDocLoader::DoFireOnStateChange \turiloader/base/nsDocLoader.cpp:1351\n8 \txul.dll \tnsDocLoader::doStopDocumentLoad \turiloader/base/nsDocLoader.cpp:942\n9 \txul.dll \tnsDocLoader::DocLoaderIsEmpty \turiloader/base/nsDocLoader.cpp:820\n10 \txul.dll \tnsDocLoader::OnStopRequest \turiloader/base/nsDocLoader.cpp:704\n11 \txul.dll \tnsLoadGroup::RemoveRequest \tnetwerk/base/src/nsLoadGroup.cpp:698\n12 \txul.dll \tnsLoadGroup::QueryInterface \tnetwerk/base/src/nsLoadGroup.cpp:177\n13 \txul.dll \tnsDocument::UnblockOnload \tcontent/base/src/nsDocument.cpp:7329\n14 \txul.dll \tnsRunnable::Release \tobj-firefox/xpcom/build/nsThreadUtils.cpp:30\n15 \txul.dll \tnsThread::ProcessNextEvent \txpcom/threads/nsThread.cpp:626\n16 \txul.dll \tmozilla::ipc::MessagePump::Run \tipc/glue/MessagePump.cpp:82\n17 \txul.dll \tMessageLoop::RunHandler \tipc/chromium/src/base/message_loop.cc:208\n18 \txul.dll \tMessageLoop::Run \tipc/chromium/src/base/message_loop.cc:182\n19 \txul.dll \tnsBaseAppShell::Run \twidget/xpwidgets/nsBaseAppShell.cpp:163\n20 \txul.dll \tnsAppShell::Run \twidget/windows/nsAppShell.cpp:232\n21 \txul.dll \tnsAppStartup::Run \ttoolkit/components/startup/nsAppStartup.cpp:290\n22 \txul.dll \tXREMain::XRE_mainRun \ttoolkit/xre/nsAppRunner.cpp:3794\n23 \txul.dll \tXREMain::XRE_main \ttoolkit/xre/nsAppRunner.cpp:3860\n24 \txul.dll \tXRE_main \ttoolkit/xre/nsAppRunner.cpp:3935\n25 \tfirefox.exe \twmain \ttoolkit/xre/nsWindowsWMain.cpp:105\n\nMore reports at:\nhttps://crash-stats.mozilla.com/report/list?signature=nsDocLoader%3A%3ADoFireOnStateChange%28nsIWebProgress*+const%2C+nsIRequest*+const%2C+int%26%2C+tag_nsresult%29",
      "matched_patterns": [
        "ns[A-Z]\\w+::\\w+"
      ],
      "parsed_frames": [
        {
          "frame_index": 7,
          "module": "xul.dll",
          "function": "nsDocLoader::DoFireOnStateChange",
          "file": "uriloader/base/nsDocLoader.cpp",
          "line": 1351,
          "raw": "7 \txul.dll \tnsDocLoader::DoFireOnStateChange \turiloader/base/nsDocLoader.cpp:1351"
        },
        {
          "frame_index": 8,
          "module": "xul.dll",
          "function": "nsDocLoader::doStopDocumentLoad",
          "file": "uriloader/base/nsDocLoader.cpp",
          "line": 942,
          "raw": "8 \txul.dll \tnsDocLoader::doStopDocumentLoad \turiloader/base/nsDocLoader.cpp:942"
        },
        {
          "frame_index": 9,
          "module": "xul.dll",
          "function": "nsDocLoader::DocLoaderIsEmpty",
          "file": "uriloader/base/nsDocLoader.cpp",
          "line": 820,
          "raw": "9 \txul.dll \tnsDocLoader::DocLoaderIsEmpty \turiloader/base/nsDocLoader.cpp:820"
        },
        {
          "frame_index": 10,
          "module": "xul.dll",
          "function": "nsDocLoader::OnStopRequest",
          "file": "uriloader/base/nsDocLoader.cpp",
          "line": 704,
          "raw": "10 \txul.dll \tnsDocLoader::OnStopRequest \turiloader/base/nsDocLoader.cpp:704"
        },
        {
          "frame_index": 11,
          "module": "xul.dll",
          "function": "nsLoadGroup::RemoveRequest",
          "file": "netwerk/base/src/nsLoadGroup.cpp",
          "line": 698,
          "raw": "11 \txul.dll \tnsLoadGroup::RemoveRequest \tnetwerk/base/src/nsLoadGroup.cpp:698"
        },
        {
          "frame_index": 12,
          "module": "xul.dll",
          "function": "nsLoadGroup::QueryInterface",
          "file": "netwerk/base/src/nsLoadGroup.cpp",
          "line": 177,
          "raw": "12 \txul.dll \tnsLoadGroup::QueryInterface \tnetwerk/base/src/nsLoadGroup.cpp:177"
        },
        {
          "frame_index": 13,
          "module": "xul.dll",
          "function": "nsDocument::UnblockOnload",
          "file": "content/base/src/nsDocument.cpp",
          "line": 7329,
          "raw": "13 \txul.dll \tnsDocument::UnblockOnload \tcontent/base/src/nsDocument.cpp:7329"
        },
        {
          "frame_index": 14,
          "module": "xul.dll",
          "function": "nsRunnable::Release",
          "file": "obj-firefox/xpcom/build/nsThreadUtils.cpp",
          "line": 30,
          "raw": "14 \txul.dll \tnsRunnable::Release \tobj-firefox/xpcom/build/nsThreadUtils.cpp:30"
        },
        {
          "frame_index": 15,
          "module": "xul.dll",
          "function": "nsThread::ProcessNextEvent",
          "file": "xpcom/threads/nsThread.cpp",
          "line": 626,
          "raw": "15 \txul.dll \tnsThread::ProcessNextEvent \txpcom/threads/nsThread.cpp:626"
        },
        {
          "frame_index": 16,
          "module": "xul.dll",
          "function": "mozilla::ipc::MessagePump::Run",
          "file": "ipc/glue/MessagePump.cpp",
          "line": 82,
          "raw": "16 \txul.dll \tmozilla::ipc::MessagePump::Run \tipc/glue/MessagePump.cpp:82"
        },
        {
          "frame_index": 17,
          "module": "xul.dll",
          "function": "MessageLoop::RunHandler",
          "file": "ipc/chromium/src/base/message_loop.cc",
          "line": 208,
          "raw": "17 \txul.dll \tMessageLoop::RunHandler \tipc/chromium/src/base/message_loop.cc:208"
        },
        {
          "frame_index": 18,
          "module": "xul.dll",
          "function": "MessageLoop::Run",
          "file": "ipc/chromium/src/base/message_loop.cc",
          "line": 182,
          "raw": "18 \txul.dll \tMessageLoop::Run \tipc/chromium/src/base/message_loop.cc:182"
        },
        {
          "frame_index": 19,
          "module": "xul.dll",
          "function": "nsBaseAppShell::Run",
          "file": "widget/xpwidgets/nsBaseAppShell.cpp",
          "line": 163,
          "raw": "19 \txul.dll \tnsBaseAppShell::Run \twidget/xpwidgets/nsBaseAppShell.cpp:163"
        },
        {
          "frame_index": 20,
          "module": "xul.dll",
          "function": "nsAppShell::Run",
          "file": "widget/windows/nsAppShell.cpp",
          "line": 232,
          "raw": "20 \txul.dll \tnsAppShell::Run \twidget/windows/nsAppShell.cpp:232"
        },
        {
          "frame_index": 21,
          "module": "xul.dll",
          "function": "nsAppStartup::Run",
          "file": "toolkit/components/startup/nsAppStartup.cpp",
          "line": 290,
          "raw": "21 \txul.dll \tnsAppStartup::Run \ttoolkit/components/startup/nsAppStartup.cpp:290"
        },
        {
          "frame_index": 22,
          "module": "xul.dll",
          "function": "XREMain::XRE_mainRun",
          "file": "toolkit/xre/nsAppRunner.cpp",
          "line": 3794,
          "raw": "22 \txul.dll \tXREMain::XRE_mainRun \ttoolkit/xre/nsAppRunner.cpp:3794"
        },
        {
          "frame_index": 23,
          "module": "xul.dll",
          "function": "XREMain::XRE_main",
          "file": "toolkit/xre/nsAppRunner.cpp",
          "line": 3860,
          "raw": "23 \txul.dll \tXREMain::XRE_main \ttoolkit/xre/nsAppRunner.cpp:3860"
        },
        {
          "frame_index": 24,
          "module": "xul.dll",
          "function": "XRE_main",
          "file": "toolkit/xre/nsAppRunner.cpp",
          "line": 3935,
          "raw": "24 \txul.dll \tXRE_main \ttoolkit/xre/nsAppRunner.cpp:3935"
        }
      ],
      "frame_count": 18
    }
  ],
  "has_stack_traces": true,
  "stack_trace_count": 1,
  "total_parsed_frames": 18
}