{
  "bug_id": "577201",
  "summary": "Firefox 4.0 Beta1 crashes when trying to copy something from web page [@ nsPurpleBuffer::SelectPointers] [@ ns_if_addref<nsISupports*>(nsISupports*)]",
  "status": "RESOLVED",
  "resolution": "FIXED",
  "product": "Firefox",
  "component": "General",
  "version": "unspecified",
  "severity": "critical",
  "priority": "--",
  "creation_time": "2010-07-07T07:26:48Z",
  "last_change_time": "2011-06-09T21:58:52Z",
  "is_recent": false,
  "crash_signature_raw": "[@ nsPurpleBuffer::SelectPointers]\n[@ ns_if_addref<nsISupports*>(nsISupports*)]",
  "crash_signatures": [
    "nsPurpleBuffer::SelectPointers",
    "ns_if_addref<nsISupports*>(nsISupports*)"
  ],
  "keywords": [
    "crash"
  ],
  "regressed_by": [],
  "regressions": [],
  "bugzilla_url": "https://bugzilla.mozilla.org/show_bug.cgi?id=577201",
  "socorro_links": [],
  "socorro_crash_ids": [],
  "has_socorro_link": false,
  "has_direct_crash_id": false,
  "stack_traces": [
    {
      "comment_id": 4784236,
      "comment_count": 1,
      "creator": "timeless@bemail.org",
      "creation_time": "2010-07-07T07:37:08Z",
      "raw_text": "Please try safe mode (you have 3 extensions)\n\nSignature\txul.dll@0xb215f0\nUUID\t7b968905-8ed9-4a97-9a6a-acbb52100707\nTime \t2010-07-07 00:22:56.290958\nUptime\t235\nLast Crash\t280 seconds (4.7 minutes) before submission\nInstall Age\t2405 seconds (40.1 minutes) since version was first installed.\nProduct\tFirefox\nVersion\t4.0b1\nBuild ID\t20100630141702\nBranch\t2.0\nOS\tWindows NT\nOS Version\t6.1.7600\nCPU\tx86\nCPU Info\tGenuineIntel family 6 model 37 stepping 2\nCrash Reason\tEXCEPTION_ACCESS_VIOLATION\nCrash Address\t0x565e15f0\nUser Comments\t\nProcessor Notes \t\nEMCheckCompatibility\tFalse\nCrashing Thread\nFrame \tModule \tSignature [Expand] \tSource\n0 \txul.dll \txul.dll@0xb215f0 \t\n1 \txul.dll \tnsPurpleBuffer::SelectPointers \txpcom/base/nsCycleCollector.cpp:913\n2 \txul.dll \tnsCycleCollector::BeginCollection \txpcom/base/nsCycleCollector.cpp:2608\n3 \txul.dll \tXPCCycleCollectGCCallback \tjs/src/xpconnect/src/nsXPConnect.cpp:361\n4 \tmozjs.dll \tGC \tjs/src/jsgc.cpp:2797\n5 \tmozjs.dll \tGCUntilDone \tjs/src/jsgc.cpp:3156\n6 \tmozjs.dll \tjs_GC \tjs/src/jsgc.cpp:3207\n7 \tmozjs.dll \tJS_GC \tjs/src/jsapi.cpp:2317\n8 \txul.dll \tnsXPConnect::Collect \tjs/src/xpconnect/src/nsXPConnect.cpp:448\n\nExtension \tExtension Id \tVersion \tCurrent?\nIDM CC \tmozilla_cc@internetdownloadmanager.com \t6.9.7 \t6.9.1\nTest Pilot \ttestpilot@labs.mozilla.com \t1.0rc1 \tcurrent\nLastPass Password Manager \tsupport@lastpass.com \t1.68.2 \tcurrent\nWOT - Safe Browsing Tool \t{a0d7ccb3-214d-498b-b4aa-0e8fda9a7bf7} \t20100503 \tcurrent\n\t{972ce4c6-7e08-4474-a285-3208198ce6fd} \t4.0b1 \t\n\nSignature\tns_if_addref<nsISupports*>(nsISupports*)\nUUID\t66b345ee-910f-4ad5-98af-5a5242100707\nTime \t2010-07-07 00:18:33.702856\nUptime\t9\nLast Crash\t12 seconds before submission\nInstall Age\t2095 seconds (34.9 minutes) since version was first installed.\nProduct\tFirefox\nVersion\t4.0b1\nBuild ID\t20100630141702\nBranch\t2.0\nOS\tWindows NT\nOS Version\t6.1.7600\nCPU\tx86\nCPU Info\tGenuineIntel family 6 model 37 stepping 2\nCrash Reason\tEXCEPTION_ACCESS_VIOLATION\nCrash Address\t0x5\nUser Comments\tBrowser crashes when you copy text from it: Open fireofx 4.0 B1 Type About:crashes in address bar copy one of the crash report Browser crashes Report : 6ca9c9ed-9da1-456c-b915-760a785c3c4607-Jul-1012:47 PM7590efd6-9600-41c0-97b4-f367e77426ff07-Jul-1012:47 PM1a871546-d880-45d2-9485-ae2286cca4b307-Jul-1012:46 PMbp-09bef571-dfd2-4d97-88ed-c11802100707\nProcessor Notes \t\nEMCheckCompatibility\tFalse\nCrashing Thread\nFrame \tModule \tSignature [Expand] \tSource\n0 \txul.dll \tns_if_addref<nsISupports*> \tobj-firefox/dist/include/nsISupportsUtils.h:115\n1 \txul.dll \tnsFrame::GetContentForEvent \tlayout/generic/nsFrame.cpp:1636\n2 \txul.dll \tPresShell::HandlePositionedEvent \tlayout/base/nsPresShell.cpp:6461\n3 \txul.dll \tPresShell::HandleEvent \tlayout/base/nsPresShell.cpp:6367\n4 \txul.dll \tnsViewManager::DispatchEvent \tview/src/nsViewManager.cpp:1027\n5 \txul.dll \tHandleEvent \tview/src/nsView.cpp:160\n6 \txul.dll \tnsWindow::DispatchEvent \twidget/src/windows/nsWindow.cpp:3523\n7 \txul.dll \tnsWindow::DispatchWindowEvent \twidget/src/windows/nsWindow.cpp:3546\n8 \txul.dll \tnsWindow::DispatchMouseEvent \twidget/src/windows/nsWindow.cpp:3957\n9 \txul.dll \tnsWindow::ProcessMessage \twidget/src/windows/nsWindow.cpp:4707\n\nExtension \tExtension Id \tVersion \tCurrent?\nIDM CC \tmozilla_cc@internetdownloadmanager.com \t6.9.7 \t6.9.1\nTest Pilot \ttestpilot@labs.mozilla.com \t1.0rc1 \tcurrent\nLastPass Password Manager \tsupport@lastpass.com \t1.68.2 \tcurrent\nWOT - Safe Browsing Tool \t{a0d7ccb3-214d-498b-b4aa-0e8fda9a7bf7} \t20100503 \tcurrent\n\t{972ce4c6-7e08-4474-a285-3208198ce6fd} \t4.0b1",
      "matched_patterns": [
        "ns[A-Z]\\w+::\\w+",
        "(?i)(crash|stack)\\s*(trace|dump|report)",
        "(?i)crashing\\s+thread"
      ],
      "parsed_frames": [
        {
          "frame_index": 0,
          "module": "xul.dll",
          "function": "xul.dll@0xb215f0",
          "file": "",
          "line": null,
          "raw": "0 \txul.dll \txul.dll@0xb215f0"
        },
        {
          "frame_index": 1,
          "module": "xul.dll",
          "function": "nsPurpleBuffer::SelectPointers",
          "file": "xpcom/base/nsCycleCollector.cpp",
          "line": 913,
          "raw": "1 \txul.dll \tnsPurpleBuffer::SelectPointers \txpcom/base/nsCycleCollector.cpp:913"
        },
        {
          "frame_index": 2,
          "module": "xul.dll",
          "function": "nsCycleCollector::BeginCollection",
          "file": "xpcom/base/nsCycleCollector.cpp",
          "line": 2608,
          "raw": "2 \txul.dll \tnsCycleCollector::BeginCollection \txpcom/base/nsCycleCollector.cpp:2608"
        },
        {
          "frame_index": 3,
          "module": "xul.dll",
          "function": "XPCCycleCollectGCCallback",
          "file": "js/src/xpconnect/src/nsXPConnect.cpp",
          "line": 361,
          "raw": "3 \txul.dll \tXPCCycleCollectGCCallback \tjs/src/xpconnect/src/nsXPConnect.cpp:361"
        },
        {
          "frame_index": 4,
          "module": "mozjs.dll",
          "function": "GC",
          "file": "js/src/jsgc.cpp",
          "line": 2797,
          "raw": "4 \tmozjs.dll \tGC \tjs/src/jsgc.cpp:2797"
        },
        {
          "frame_index": 5,
          "module": "mozjs.dll",
          "function": "GCUntilDone",
          "file": "js/src/jsgc.cpp",
          "line": 3156,
          "raw": "5 \tmozjs.dll \tGCUntilDone \tjs/src/jsgc.cpp:3156"
        },
        {
          "frame_index": 6,
          "module": "mozjs.dll",
          "function": "js_GC",
          "file": "js/src/jsgc.cpp",
          "line": 3207,
          "raw": "6 \tmozjs.dll \tjs_GC \tjs/src/jsgc.cpp:3207"
        },
        {
          "frame_index": 7,
          "module": "mozjs.dll",
          "function": "JS_GC",
          "file": "js/src/jsapi.cpp",
          "line": 2317,
          "raw": "7 \tmozjs.dll \tJS_GC \tjs/src/jsapi.cpp:2317"
        },
        {
          "frame_index": 8,
          "module": "xul.dll",
          "function": "nsXPConnect::Collect",
          "file": "js/src/xpconnect/src/nsXPConnect.cpp",
          "line": 448,
          "raw": "8 \txul.dll \tnsXPConnect::Collect \tjs/src/xpconnect/src/nsXPConnect.cpp:448"
        },
        {
          "frame_index": 0,
          "module": "xul.dll",
          "function": "ns_if_addref<nsISupports*>",
          "file": "obj-firefox/dist/include/nsISupportsUtils.h",
          "line": 115,
          "raw": "0 \txul.dll \tns_if_addref<nsISupports*> \tobj-firefox/dist/include/nsISupportsUtils.h:115"
        },
        {
          "frame_index": 1,
          "module": "xul.dll",
          "function": "nsFrame::GetContentForEvent",
          "file": "layout/generic/nsFrame.cpp",
          "line": 1636,
          "raw": "1 \txul.dll \tnsFrame::GetContentForEvent \tlayout/generic/nsFrame.cpp:1636"
        },
        {
          "frame_index": 2,
          "module": "xul.dll",
          "function": "PresShell::HandlePositionedEvent",
          "file": "layout/base/nsPresShell.cpp",
          "line": 6461,
          "raw": "2 \txul.dll \tPresShell::HandlePositionedEvent \tlayout/base/nsPresShell.cpp:6461"
        },
        {
          "frame_index": 3,
          "module": "xul.dll",
          "function": "PresShell::HandleEvent",
          "file": "layout/base/nsPresShell.cpp",
          "line": 6367,
          "raw": "3 \txul.dll \tPresShell::HandleEvent \tlayout/base/nsPresShell.cpp:6367"
        },
        {
          "frame_index": 4,
          "module": "xul.dll",
          "function": "nsViewManager::DispatchEvent",
          "file": "view/src/nsViewManager.cpp",
          "line": 1027,
          "raw": "4 \txul.dll \tnsViewManager::DispatchEvent \tview/src/nsViewManager.cpp:1027"
        },
        {
          "frame_index": 5,
          "module": "xul.dll",
          "function": "HandleEvent",
          "file": "view/src/nsView.cpp",
          "line": 160,
          "raw": "5 \txul.dll \tHandleEvent \tview/src/nsView.cpp:160"
        },
        {
          "frame_index": 6,
          "module": "xul.dll",
          "function": "nsWindow::DispatchEvent",
          "file": "widget/src/windows/nsWindow.cpp",
          "line": 3523,
          "raw": "6 \txul.dll \tnsWindow::DispatchEvent \twidget/src/windows/nsWindow.cpp:3523"
        },
        {
          "frame_index": 7,
          "module": "xul.dll",
          "function": "nsWindow::DispatchWindowEvent",
          "file": "widget/src/windows/nsWindow.cpp",
          "line": 3546,
          "raw": "7 \txul.dll \tnsWindow::DispatchWindowEvent \twidget/src/windows/nsWindow.cpp:3546"
        },
        {
          "frame_index": 8,
          "module": "xul.dll",
          "function": "nsWindow::DispatchMouseEvent",
          "file": "widget/src/windows/nsWindow.cpp",
          "line": 3957,
          "raw": "8 \txul.dll \tnsWindow::DispatchMouseEvent \twidget/src/windows/nsWindow.cpp:3957"
        },
        {
          "frame_index": 9,
          "module": "xul.dll",
          "function": "nsWindow::ProcessMessage",
          "file": "widget/src/windows/nsWindow.cpp",
          "line": 4707,
          "raw": "9 \txul.dll \tnsWindow::ProcessMessage \twidget/src/windows/nsWindow.cpp:4707"
        }
      ],
      "frame_count": 19
    }
  ],
  "has_stack_traces": true,
  "stack_trace_count": 1,
  "total_parsed_frames": 19
}