{
  "bug_id": "1998057",
  "summary": "Crash in [@ libc.so.6 | libc.so.6 | libc.so.6 | mozilla::ipc::MessageChannel::WaitForSyncNotify | mozilla::ipc::MessageChannel::Send | mozilla::ipc::IProtocol::ChannelSend | mozilla::layers::PCompositorBridgeChild::SendWillClose]",
  "status": "RESOLVED",
  "resolution": "FIXED",
  "product": "Firefox",
  "component": "Tabbed Browser",
  "version": "unspecified",
  "severity": "--",
  "priority": "--",
  "creation_time": "2025-11-04T00:41:10Z",
  "last_change_time": "2025-11-26T20:26:14Z",
  "is_recent": true,
  "crash_signature_raw": "[@ libc.so.6 | libc.so.6 | libc.so.6 | mozilla::ipc::MessageChannel::WaitForSyncNotify | mozilla::ipc::MessageChannel::Send | mozilla::ipc::IProtocol::ChannelSend | mozilla::layers::PCompositorBridgeChild::SendWillClose]\r\n[@ libc.so.6 | libc.so.6 | firefox-nightly-bin]\n[@ mozilla::ipc::MessageChannel::WaitForSyncNotify | mozilla::ipc::MessageChannel::Send | mozilla::ipc::IProtocol::ChannelSend | mozilla::layers::PCompositorBridgeChild::SendWillClose]",
  "crash_signatures": [
    "libc.so.6 | libc.so.6 | libc.so.6 | mozilla::ipc::MessageChannel::WaitForSyncNotify | mozilla::ipc::MessageChannel::Send | mozilla::ipc::IProtocol::ChannelSend | mozilla::layers::PCompositorBridgeChild::SendWillClose",
    "libc.so.6 | libc.so.6 | firefox-nightly-bin",
    "mozilla::ipc::MessageChannel::WaitForSyncNotify | mozilla::ipc::MessageChannel::Send | mozilla::ipc::IProtocol::ChannelSend | mozilla::layers::PCompositorBridgeChild::SendWillClose"
  ],
  "keywords": [
    "crash",
    "regression"
  ],
  "regressed_by": [
    1994879
  ],
  "regressions": [],
  "bugzilla_url": "https://bugzilla.mozilla.org/show_bug.cgi?id=1998057",
  "socorro_links": [
    {
      "url": "https://crash-stats.mozilla.org/report/index/cd9e314a-ce0b-4165-be80-a42ab0251031",
      "crash_id": "cd9e314a-ce0b-4165-be80-a42ab0251031",
      "comment_index": 0,
      "comment_text": "\nCrash report: https://crash-stats.mozilla.org/report/index/cd9e314a-ce0b-4165-be80-a42ab0251031\n\n\n\nReason: ```SIGABRT```\n\n\nTop 10 frames of crashing thread:\n```\n0  libc.so.6  libc.so.6@0x7a982  \n1  libc.so.6  libc.so.6@0x6f2ab  \n2  libc.so.6  libc.so.6@0x7197d  \n3  firefox-bin  mozilla::detail::ConditionVariableImpl::wait  mozglue/misc/ConditionVariable_posix.cpp:104\n3  firefox-bin  mozilla::detail::ConditionVariableImpl::wait_for  mozglue/misc/ConditionVariable_posix.cpp:111\n4  libxul.so  mozilla::OffTheBooksCondVar::Wait  xpcom/threads/CondVar.h:65\n4  libxul.so  mozilla::Monitor::Wait  xpcom/threads/Monitor.h:39\n4  libxul.so  mozilla::ipc::MessageChannel::WaitForSyncNotify  ipc/glue/MessageChannel.cpp:1842\n4  libxul.so  mozilla::ipc::MessageChannel::Send  ipc/glue/MessageChannel.cpp:1337\n4  libxul.so  mozilla::ipc::IProtocol::ChannelSend  ipc/glue/ProtocolUtils.cpp:500\n```\n\n\n\nBy querying Nightly crashes reported within the last 2 months, here are some insights about the signature:\n\n- **First crash report:** 2025-10-31\n- **Process type:** Parent\n- **Is startup crash:** No\n- **Has user comments:** No\n- **Is null crash:** No\n\n\n\n\n\n\nBy analyzing the backtrace, the regression may have been introduced by a patch [1] to fix Bug 1994879.\n\n[1] https://hg.mozilla.org/mozilla-central/rev?node=8c5286558339\n\n\n\n:jswinarton, since you are the author of the potential regressor, could you please take a look?"
    }
  ],
  "socorro_crash_ids": [
    "cd9e314a-ce0b-4165-be80-a42ab0251031"
  ],
  "has_socorro_link": true,
  "has_direct_crash_id": true,
  "stack_traces": [
    {
      "comment_id": 17746947,
      "comment_count": 0,
      "creator": "release-mgmt-account-bot@mozilla.tld",
      "creation_time": "2025-11-04T00:41:10Z",
      "raw_text": "\nCrash report: https://crash-stats.mozilla.org/report/index/cd9e314a-ce0b-4165-be80-a42ab0251031\n\n\n\nReason: ```SIGABRT```\n\n\nTop 10 frames of crashing thread:\n```\n0  libc.so.6  libc.so.6@0x7a982  \n1  libc.so.6  libc.so.6@0x6f2ab  \n2  libc.so.6  libc.so.6@0x7197d  \n3  firefox-bin  mozilla::detail::ConditionVariableImpl::wait  mozglue/misc/ConditionVariable_posix.cpp:104\n3  firefox-bin  mozilla::detail::ConditionVariableImpl::wait_for  mozglue/misc/ConditionVariable_posix.cpp:111\n4  libxul.so  mozilla::OffTheBooksCondVar::Wait  xpcom/threads/CondVar.h:65\n4  libxul.so  mozilla::Monitor::Wait  xpcom/threads/Monitor.h:39\n4  libxul.so  mozilla::ipc::MessageChannel::WaitForSyncNotify  ipc/glue/MessageChannel.cpp:1842\n4  libxul.so  mozilla::ipc::MessageChannel::Send  ipc/glue/MessageChannel.cpp:1337\n4  libxul.so  mozilla::ipc::IProtocol::ChannelSend  ipc/glue/ProtocolUtils.cpp:500\n```\n\n\n\nBy querying Nightly crashes reported within the last 2 months, here are some insights about the signature:\n\n- **First crash report:** 2025-10-31\n- **Process type:** Parent\n- **Is startup crash:** No\n- **Has user comments:** No\n- **Is null crash:** No\n\n\n\n\n\n\nBy analyzing the backtrace, the regression may have been introduced by a patch [1] to fix Bug 1994879.\n\n[1] https://hg.mozilla.org/mozilla-central/rev?node=8c5286558339\n\n\n\n:jswinarton, since you are the author of the potential regressor, could you please take a look?",
      "matched_patterns": [
        "(?i)(crash|stack)\\s*(trace|dump|report)",
        "(?i)crashing\\s+thread"
      ],
      "parsed_frames": [
        {
          "frame_index": 4,
          "module": "libxul.so",
          "function": "mozilla::OffTheBooksCondVar::Wait",
          "file": "xpcom/threads/CondVar.h",
          "line": 65,
          "raw": "4  libxul.so  mozilla::OffTheBooksCondVar::Wait  xpcom/threads/CondVar.h:65"
        },
        {
          "frame_index": 4,
          "module": "libxul.so",
          "function": "mozilla::Monitor::Wait",
          "file": "xpcom/threads/Monitor.h",
          "line": 39,
          "raw": "4  libxul.so  mozilla::Monitor::Wait  xpcom/threads/Monitor.h:39"
        },
        {
          "frame_index": 4,
          "module": "libxul.so",
          "function": "mozilla::ipc::MessageChannel::WaitForSyncNotify",
          "file": "ipc/glue/MessageChannel.cpp",
          "line": 1842,
          "raw": "4  libxul.so  mozilla::ipc::MessageChannel::WaitForSyncNotify  ipc/glue/MessageChannel.cpp:1842"
        },
        {
          "frame_index": 4,
          "module": "libxul.so",
          "function": "mozilla::ipc::MessageChannel::Send",
          "file": "ipc/glue/MessageChannel.cpp",
          "line": 1337,
          "raw": "4  libxul.so  mozilla::ipc::MessageChannel::Send  ipc/glue/MessageChannel.cpp:1337"
        },
        {
          "frame_index": 4,
          "module": "libxul.so",
          "function": "mozilla::ipc::IProtocol::ChannelSend",
          "file": "ipc/glue/ProtocolUtils.cpp",
          "line": 500,
          "raw": "4  libxul.so  mozilla::ipc::IProtocol::ChannelSend  ipc/glue/ProtocolUtils.cpp:500"
        }
      ],
      "frame_count": 5
    }
  ],
  "has_stack_traces": true,
  "stack_trace_count": 1,
  "total_parsed_frames": 5
}